Workbook

Sheet Risk Register
A1: Risk Register LumiPay v1.0 (14 Okt 2026): Analisis Risiko (langkah 3)
A2: Penilaian ini untuk kondisi saat ini (sebelum penanganan). Dampak diambil dari dimensi yang paling parah (MAX), lalu skor = kemungkinan x dampak.
A3: Legenda: sel biru berlatar kuning = nilai penilaian (boleh diubah, skala 1 sampai 5). Sel hitam = rumus, jangan diketik manual. Batas level dan penerimaan ada di sheet Kriteria.
A5: ID | B5: Aset | C5: Skenario risiko | D5: Pemilik risiko | E5: Kemungkinan (1-5) | F5: Dampak operasional layanan (1-5) | G5: Dampak finansial (1-5) | H5: Dampak reputasi (1-5) | I5: Dampak (maks) | J5: Skor | K5: Level | L5: Keputusan awal | M5: Alasan penilaian | N5: Kunci urutan prioritas (bantuan, jangan diubah)
A6: R-01 | B6: A-01 Database transaksi | C6: Data transaksi dicuri atau dimanipulasi lewat celah aplikasi | D6: Head of Engineering | E6: 3 | F6: 3 | G6: 4 | H6: 4 | I6: =MAX(F6:H6) -> 4 | J6: =E6*I6 -> 12 | K6: =IF(J6<=Kriteria!$B$3,"Rendah",IF(J6<=Kriteria!$B$4,"Sedang",IF(J6<=Kriteria!$B$5,"Tinggi","Kritis"))) -> Tinggi | L6: =IF(J6>Kriteria!$B$6,"Perlu ditangani",IF(J6>Kriteria!$B$3,"Dapat diterima, perlu persetujuan pemilik risiko","Diterima")) -> Perlu ditangani | M6: Validasi input lemah dan patch terlambat; dampak terbesar pada finansial dan reputasi. | N6: =J6+I6/100+E6/10000-ROW()/10000000 -> 12.040299
A7: R-02 | B7: A-02 Data KYC pengguna | C7: Data KTP dan swafoto pengguna bocor atau disalahgunakan | D7: Compliance Officer | E7: 3 | F7: 2 | G7: 3 | H7: 4 | I7: =MAX(F7:H7) -> 4 | J7: =E7*I7 -> 12 | K7: =IF(J7<=Kriteria!$B$3,"Rendah",IF(J7<=Kriteria!$B$4,"Sedang",IF(J7<=Kriteria!$B$5,"Tinggi","Kritis"))) -> Tinggi | L7: =IF(J7>Kriteria!$B$6,"Perlu ditangani",IF(J7>Kriteria!$B$3,"Dapat diterima, perlu persetujuan pemilik risiko","Diterima")) -> Perlu ditangani | M7: Hak akses luas dan belum ada MFA; kebocoran data pribadi memukul reputasi. | N7: =J7+I7/100+E7/10000-ROW()/10000000 -> 12.040299
A8: R-03 | B8: A-02 Data KYC pengguna | C8: File KYC terekspos ke internet | D8: Head of Infrastructure | E8: 2 | F8: 1 | G8: 3 | H8: 5 | I8: =MAX(F8:H8) -> 5 | J8: =E8*I8 -> 10 | K8: =IF(J8<=Kriteria!$B$3,"Rendah",IF(J8<=Kriteria!$B$4,"Sedang",IF(J8<=Kriteria!$B$5,"Tinggi","Kritis"))) -> Tinggi | L8: =IF(J8>Kriteria!$B$6,"Perlu ditangani",IF(J8>Kriteria!$B$3,"Dapat diterima, perlu persetujuan pemilik risiko","Diterima")) -> Perlu ditangani | M8: Salah konfigurasi jarang terjadi tetapi mungkin; jika terekspos, kepercayaan publik sangat terpukul. | N8: =J8+I8/100+E8/10000-ROW()/10000000 -> 10.050199
A9: R-04 | B9: A-03 Saldo dan ledger | C9: Saldo atau mutasi diubah tanpa terdeteksi | D9: Head of Finance Operations | E9: 2 | F9: 2 | G9: 5 | H9: 4 | I9: =MAX(F9:H9) -> 5 | J9: =E9*I9 -> 10 | K9: =IF(J9<=Kriteria!$B$3,"Rendah",IF(J9<=Kriteria!$B$4,"Sedang",IF(J9<=Kriteria!$B$5,"Tinggi","Kritis"))) -> Tinggi | L9: =IF(J9>Kriteria!$B$6,"Perlu ditangani",IF(J9>Kriteria!$B$3,"Dapat diterima, perlu persetujuan pemilik risiko","Diterima")) -> Perlu ditangani | M9: Tanpa pemisahan tugas dan rekonsiliasi manual; kejadian jarang, tetapi kerugian finansial besar. | N9: =J9+I9/100+E9/10000-ROW()/10000000 -> 10.050199
A10: R-05 | B10: A-04 Kunci enkripsi dan secret | C10: Kunci jatuh ke penyerang sehingga data terenkripsi bisa dibuka | D10: Head of Security | E10: 3 | F10: 3 | G10: 4 | H10: 4 | I10: =MAX(F10:H10) -> 4 | J10: =E10*I10 -> 12 | K10: =IF(J10<=Kriteria!$B$3,"Rendah",IF(J10<=Kriteria!$B$4,"Sedang",IF(J10<=Kriteria!$B$5,"Tinggi","Kritis"))) -> Tinggi | L10: =IF(J10>Kriteria!$B$6,"Perlu ditangani",IF(J10>Kriteria!$B$3,"Dapat diterima, perlu persetujuan pemilik risiko","Diterima")) -> Perlu ditangani | M10: Secret di kode atau chat membuat kebocoran cukup mungkin; efeknya berantai ke banyak sistem. | N10: =J10+I10/100+E10/10000-ROW()/10000000 -> 12.040299
A11: R-06 | B11: A-05 Kode sumber dan pipeline CI/CD | C11: Kode sumber bocor sehingga celah aplikasi dan logika bisnis terlihat pihak yang tidak berwenang | D11: Head of Engineering | E11: 3 | F11: 2 | G11: 2 | H11: 3 | I11: =MAX(F11:H11) -> 3 | J11: =E11*I11 -> 9 | K11: =IF(J11<=Kriteria!$B$3,"Rendah",IF(J11<=Kriteria!$B$4,"Sedang",IF(J11<=Kriteria!$B$5,"Tinggi","Kritis"))) -> Sedang | L11: =IF(J11>Kriteria!$B$6,"Perlu ditangani",IF(J11>Kriteria!$B$3,"Dapat diterima, perlu persetujuan pemilik risiko","Diterima")) -> Dapat diterima, perlu persetujuan pemilik risiko | M11: Akun mantan karyawan masih aktif dan tanpa MFA, repositori bisa dipublikasikan tanpa kontrol; kebocoran kode membuka celah aplikasi dan kekayaan intelektual. Secret di dalam kode dicakup R-05, perubahan kode tanpa izin dicakup R-07. | N11: =J11+I11/100+E11/10000-ROW()/10000000 -> 9.0302989
A12: R-07 | B12: A-05 Kode sumber dan pipeline CI/CD | C12: Kode atau pipeline diubah tanpa izin sehingga kode berbahaya masuk ke produksi dan dana atau data pengguna disalahgunakan | D12: Head of Engineering | E12: 3 | F12: 4 | G12: 5 | H12: 5 | I12: =MAX(F12:H12) -> 5 | J12: =E12*I12 -> 15 | K12: =IF(J12<=Kriteria!$B$3,"Rendah",IF(J12<=Kriteria!$B$4,"Sedang",IF(J12<=Kriteria!$B$5,"Tinggi","Kritis"))) -> Tinggi | L12: =IF(J12>Kriteria!$B$6,"Perlu ditangani",IF(J12>Kriteria!$B$3,"Dapat diterima, perlu persetujuan pemilik risiko","Diterima")) -> Perlu ditangani | M12: Kerentanan akses sama dengan R-06 (tanpa MFA, akun mantan karyawan aktif), ditambah belum ada branch protection dan review wajib. Kode berbahaya di aplikasi pembayaran bisa mengalihkan dana dan memengaruhi semua pengguna, jadi dampak dinilai paling parah. Beda dengan R-06: ini soal integritas, bukan kerahasiaan. | N12: =J12+I12/100+E12/10000-ROW()/10000000 -> 15.050299
A13: R-08 | B13: A-06 Dokumen kebijakan dan kontrak | C13: Kebijakan usang atau berubah tanpa persetujuan, kewajiban hukum terlewat | D13: Compliance Officer | E13: 3 | F13: 1 | G13: 2 | H13: 2 | I13: =MAX(F13:H13) -> 2 | J13: =E13*I13 -> 6 | K13: =IF(J13<=Kriteria!$B$3,"Rendah",IF(J13<=Kriteria!$B$4,"Sedang",IF(J13<=Kriteria!$B$5,"Tinggi","Kritis"))) -> Sedang | L13: =IF(J13>Kriteria!$B$6,"Perlu ditangani",IF(J13>Kriteria!$B$3,"Dapat diterima, perlu persetujuan pemilik risiko","Diterima")) -> Dapat diterima, perlu persetujuan pemilik risiko | M13: Tanpa kontrol versi; dampak operasional kecil, tetapi bisa memicu temuan kepatuhan. | N13: =J13+I13/100+E13/10000-ROW()/10000000 -> 6.0202987
A14: R-09 | B14: A-07 Aplikasi mobile | C14: Aplikasi palsu mencuri kredensial pengguna | D14: Product Owner | E14: 3 | F14: 1 | G14: 3 | H14: 3 | I14: =MAX(F14:H14) -> 3 | J14: =E14*I14 -> 9 | K14: =IF(J14<=Kriteria!$B$3,"Rendah",IF(J14<=Kriteria!$B$4,"Sedang",IF(J14<=Kriteria!$B$5,"Tinggi","Kritis"))) -> Sedang | L14: =IF(J14>Kriteria!$B$6,"Perlu ditangani",IF(J14>Kriteria!$B$3,"Dapat diterima, perlu persetujuan pemilik risiko","Diterima")) -> Dapat diterima, perlu persetujuan pemilik risiko | M14: Aplikasi tiruan cukup umum di sektor dompet digital; tidak ada proteksi integritas aplikasi. | N14: =J14+I14/100+E14/10000-ROW()/10000000 -> 9.0302986
A15: R-10 | B15: A-08 API payment gateway | C15: API tidak tersedia, transaksi merchant gagal | D15: Head of Engineering | E15: 4 | F15: 4 | G15: 3 | H15: 3 | I15: =MAX(F15:H15) -> 4 | J15: =E15*I15 -> 16 | K15: =IF(J15<=Kriteria!$B$3,"Rendah",IF(J15<=Kriteria!$B$4,"Sedang",IF(J15<=Kriteria!$B$5,"Tinggi","Kritis"))) -> Tinggi | L15: =IF(J15>Kriteria!$B$6,"Perlu ditangani",IF(J15>Kriteria!$B$3,"Dapat diterima, perlu persetujuan pemilik risiko","Diterima")) -> Perlu ditangani | M15: Tanpa rate limiting dan proteksi DDoS yang memadai; serangan ke API pembayaran sering terjadi. | N15: =J15+I15/100+E15/10000-ROW()/10000000 -> 16.040398
A16: R-11 | B16: A-08 API payment gateway | C16: Penyerang mengakses transaksi merchant lain | D16: Head of Engineering | E16: 3 | F16: 2 | G16: 4 | H16: 4 | I16: =MAX(F16:H16) -> 4 | J16: =E16*I16 -> 12 | K16: =IF(J16<=Kriteria!$B$3,"Rendah",IF(J16<=Kriteria!$B$4,"Sedang",IF(J16<=Kriteria!$B$5,"Tinggi","Kritis"))) -> Tinggi | L16: =IF(J16>Kriteria!$B$6,"Perlu ditangani",IF(J16>Kriteria!$B$3,"Dapat diterima, perlu persetujuan pemilik risiko","Diterima")) -> Perlu ditangani | M16: Otorisasi per objek lemah; celah semacam ini umum di API. | N16: =J16+I16/100+E16/10000-ROW()/10000000 -> 12.040298
A17: R-12 | B17: A-09 Dasbor merchant | C17: Akun merchant diambil alih dan dana dialihkan | D17: Product Owner | E17: 4 | F17: 2 | G17: 3 | H17: 3 | I17: =MAX(F17:H17) -> 3 | J17: =E17*I17 -> 12 | K17: =IF(J17<=Kriteria!$B$3,"Rendah",IF(J17<=Kriteria!$B$4,"Sedang",IF(J17<=Kriteria!$B$5,"Tinggi","Kritis"))) -> Tinggi | L17: =IF(J17>Kriteria!$B$6,"Perlu ditangani",IF(J17>Kriteria!$B$3,"Dapat diterima, perlu persetujuan pemilik risiko","Diterima")) -> Perlu ditangani | M17: Credential stuffing sangat umum; MFA masih opsional. | N17: =J17+I17/100+E17/10000-ROW()/10000000 -> 12.030398
... A27: R-22 | B27: A-17 Personel kunci | C27: Pengetahuan kritis hilang dan akses mantan karyawan masih aktif | D27: Head of HR | E27: 3 | F27: 3 | G27: 2 | H27: 2 | I27: =MAX(F27:H27) -> 3 | J27: =E27*I27 -> 9 | K27: =IF(J27<=Kriteria!$B$3,"Rendah",IF(J27<=Kriteria!$B$4,"Sedang",IF(J27<=Kriteria!$B$5,"Tinggi","Kritis"))) -> Sedang | L27: =IF(J27>Kriteria!$B$6,"Perlu ditangani",IF(J27>Kriteria!$B$3,"Dapat diterima, perlu persetujuan pemilik risiko","Diterima")) -> Dapat diterima, perlu persetujuan pemilik risiko | M27: Ketergantungan pada satu orang dan offboarding tidak teratur; perputaran karyawan wajar terjadi. | N27: =J27+I27/100+E27/10000-ROW()/10000000 -> 9.0302973

Sheet Evaluasi
A1: Evaluasi Risiko LumiPay (langkah 4)
A2: Skor tiap risiko dibandingkan dengan batas penerimaan (sheet Kriteria), lalu diurutkan dari yang paling mendesak.
A3: Aturan urutan: skor tertinggi dulu; jika sama, dampak tertinggi dulu; jika masih sama, kemungkinan tertinggi dulu; terakhir urutan ID.
A4: Legenda: sel biru berlatar kuning = parameter tenggat (boleh diubah). Kolom lain berisi rumus yang membaca Risk Register.
A6: Tenggat penanganan level Tinggi (hari) | D6: 90
A7: Tenggat penanganan level Kritis (hari) | D7: 30
A9: Prioritas | B9: ID | C9: Skenario risiko | D9: Pemilik risiko | E9: Skor | F9: Level | G9: Keputusan evaluasi | H9: Tenggat penanganan | I9: Pihak yang menyetujui
A10: 1 | B10: =INDEX('Risk Register'!$A$6:$A$27,MATCH(LARGE('Risk Register'!$N$6:$N$27,$A10),'Risk Register'!$N$6:$N$27,0)) -> R-10 | C10: =INDEX('Risk Register'!$C$6:$C$27,MATCH(LARGE('Risk Register'!$N$6:$N$27,$A10),'Risk Register'!$N$6:$N$27,0)) -> API tidak tersedia, transaksi merchant gagal | D10: =INDEX('Risk Register'!$D$6:$D$27,MATCH(LARGE('Risk Register'!$N$6:$N$27,$A10),'Risk Register'!$N$6:$N$27,0)) -> Head of Engineering | E10: =INDEX('Risk Register'!$J$6:$J$27,MATCH(LARGE('Risk Register'!$N$6:$N$27,$A10),'Risk Register'!$N$6:$N$27,0)) -> 16 | F10: =INDEX('Risk Register'!$K$6:$K$27,MATCH(LARGE('Risk Register'!$N$6:$N$27,$A10),'Risk Register'!$N$6:$N$27,0)) -> Tinggi | G10: =INDEX('Risk Register'!$L$6:$L$27,MATCH(LARGE('Risk Register'!$N$6:$N$27,$A10),'Risk Register'!$N$6:$N$27,0)) -> Perlu ditangani | H10: =IF(F10="Kritis","Dalam "&$D$7&" hari",IF(F10="Tinggi","Dalam "&$D$6&" hari",IF(F10="Sedang","Tinjau tiap 6 bulan","Pantau saat tinjauan berkala"))) -> Dalam 90 hari | I10: =IF(F10="Kritis","Direksi",IF(F10="Tinggi","Manajemen (risiko sisa)",IF(F10="Sedang","Pemilik risiko","Tidak perlu"))) -> Manajemen (risiko sisa)
A11: 2 | B11: =INDEX('Risk Register'!$A$6:$A$27,MATCH(LARGE('Risk Register'!$N$6:$N$27,$A11),'Risk Register'!$N$6:$N$27,0)) -> R-18 | C11: =INDEX('Risk Register'!$C$6:$C$27,MATCH(LARGE('Risk Register'!$N$6:$N$27,$A11),'Risk Register'!$N$6:$N$27,0)) -> Karyawan menyerahkan kredensial dan penyerang masuk ke sistem | D11: =INDEX('Risk Register'!$D$6:$D$27,MATCH(LARGE('Risk Register'!$N$6:$N$27,$A11),'Risk Register'!$N$6:$N$27,0)) -> Head of IT Support | E11: =INDEX('Risk Register'!$J$6:$J$27,MATCH(LARGE('Risk Register'!$N$6:$N$27,$A11),'Risk Register'!$N$6:$N$27,0)) -> 16 | F11: =INDEX('Risk Register'!$K$6:$K$27,MATCH(LARGE('Risk Register'!$N$6:$N$27,$A11),'Risk Register'!$N$6:$N$27,0)) -> Tinggi | G11: =INDEX('Risk Register'!$L$6:$L$27,MATCH(LARGE('Risk Register'!$N$6:$N$27,$A11),'Risk Register'!$N$6:$N$27,0)) -> Perlu ditangani | H11: =IF(F11="Kritis","Dalam "&$D$7&" hari",IF(F11="Tinggi","Dalam "&$D$6&" hari",IF(F11="Sedang","Tinjau tiap 6 bulan","Pantau saat tinjauan berkala"))) -> Dalam 90 hari | I11: =IF(F11="Kritis","Direksi",IF(F11="Tinggi","Manajemen (risiko sisa)",IF(F11="Sedang","Pemilik risiko","Tidak perlu"))) -> Manajemen (risiko sisa)
A12: 3 | B12: =INDEX('Risk Register'!$A$6:$A$27,MATCH(LARGE('Risk Register'!$N$6:$N$27,$A12),'Risk Register'!$N$6:$N$27,0)) -> R-07 | C12: =INDEX('Risk Register'!$C$6:$C$27,MATCH(LARGE('Risk Register'!$N$6:$N$27,$A12),'Risk Register'!$N$6:$N$27,0)) -> Kode atau pipeline diubah tanpa izin sehingga kode berbahaya masuk ke produksi dan dana atau data pengguna disalahgunakan | D12: =INDEX('Risk Register'!$D$6:$D$27,MATCH(LARGE('Risk Register'!$N$6:$N$27,$A12),'Risk Register'!$N$6:$N$27,0)) -> Head of Engineering | E12: =INDEX('Risk Register'!$J$6:$J$27,MATCH(LARGE('Risk Register'!$N$6:$N$27,$A12),'Risk Register'!$N$6:$N$27,0)) -> 15 | F12: =INDEX('Risk Register'!$K$6:$K$27,MATCH(LARGE('Risk Register'!$N$6:$N$27,$A12),'Risk Register'!$N$6:$N$27,0)) -> Tinggi | G12: =INDEX('Risk Register'!$L$6:$L$27,MATCH(LARGE('Risk Register'!$N$6:$N$27,$A12),'Risk Register'!$N$6:$N$27,0)) -> Perlu ditangani | H12: =IF(F12="Kritis","Dalam "&$D$7&" hari",IF(F12="Tinggi","Dalam "&$D$6&" hari",IF(F12="Sedang","Tinjau tiap 6 bulan","Pantau saat tinjauan berkala"))) -> Dalam 90 hari | I12: =IF(F12="Kritis","Direksi",IF(F12="Tinggi","Manajemen (risiko sisa)",IF(F12="Sedang","Pemilik risiko","Tidak perlu"))) -> Manajemen (risiko sisa)
A13: 4 | B13: =INDEX('Risk Register'!$A$6:$A$27,MATCH(LARGE('Risk Register'!$N$6:$N$27,$A13),'Risk Register'!$N$6:$N$27,0)) -> R-01 | C13: =INDEX('Risk Register'!$C$6:$C$27,MATCH(LARGE('Risk Register'!$N$6:$N$27,$A13),'Risk Register'!$N$6:$N$27,0)) -> Data transaksi dicuri atau dimanipulasi lewat celah aplikasi | D13: =INDEX('Risk Register'!$D$6:$D$27,MATCH(LARGE('Risk Register'!$N$6:$N$27,$A13),'Risk Register'!$N$6:$N$27,0)) -> Head of Engineering | E13: =INDEX('Risk Register'!$J$6:$J$27,MATCH(LARGE('Risk Register'!$N$6:$N$27,$A13),'Risk Register'!$N$6:$N$27,0)) -> 12 | F13: =INDEX('Risk Register'!$K$6:$K$27,MATCH(LARGE('Risk Register'!$N$6:$N$27,$A13),'Risk Register'!$N$6:$N$27,0)) -> Tinggi | G13: =INDEX('Risk Register'!$L$6:$L$27,MATCH(LARGE('Risk Register'!$N$6:$N$27,$A13),'Risk Register'!$N$6:$N$27,0)) -> Perlu ditangani | H13: =IF(F13="Kritis","Dalam "&$D$7&" hari",IF(F13="Tinggi","Dalam "&$D$6&" hari",IF(F13="Sedang","Tinjau tiap 6 bulan","Pantau saat tinjauan berkala"))) -> Dalam 90 hari | I13: =IF(F13="Kritis","Direksi",IF(F13="Tinggi","Manajemen (risiko sisa)",IF(F13="Sedang","Pemilik risiko","Tidak perlu"))) -> Manajemen (risiko sisa)
A14: 5 | B14: =INDEX('Risk Register'!$A$6:$A$27,MATCH(LARGE('Risk Register'!$N$6:$N$27,$A14),'Risk Register'!$N$6:$N$27,0)) -> R-02 | C14: =INDEX('Risk Register'!$C$6:$C$27,MATCH(LARGE('Risk Register'!$N$6:$N$27,$A14),'Risk Register'!$N$6:$N$27,0)) -> Data KTP dan swafoto pengguna bocor atau disalahgunakan | D14: =INDEX('Risk Register'!$D$6:$D$27,MATCH(LARGE('Risk Register'!$N$6:$N$27,$A14),'Risk Register'!$N$6:$N$27,0)) -> Compliance Officer | E14: =INDEX('Risk Register'!$J$6:$J$27,MATCH(LARGE('Risk Register'!$N$6:$N$27,$A14),'Risk Register'!$N$6:$N$27,0)) -> 12 | F14: =INDEX('Risk Register'!$K$6:$K$27,MATCH(LARGE('Risk Register'!$N$6:$N$27,$A14),'Risk Register'!$N$6:$N$27,0)) -> Tinggi | G14: =INDEX('Risk Register'!$L$6:$L$27,MATCH(LARGE('Risk Register'!$N$6:$N$27,$A14),'Risk Register'!$N$6:$N$27,0)) -> Perlu ditangani | H14: =IF(F14="Kritis","Dalam "&$D$7&" hari",IF(F14="Tinggi","Dalam "&$D$6&" hari",IF(F14="Sedang","Tinjau tiap 6 bulan","Pantau saat tinjauan berkala"))) -> Dalam 90 hari | I14: =IF(F14="Kritis","Direksi",IF(F14="Tinggi","Manajemen (risiko sisa)",IF(F14="Sedang","Pemilik risiko","Tidak perlu"))) -> Manajemen (risiko sisa)
A15: 6 | B15: =INDEX('Risk Register'!$A$6:$A$27,MATCH(LARGE('Risk Register'!$N$6:$N$27,$A15),'Risk Register'!$N$6:$N$27,0)) -> R-05 | C15: =INDEX('Risk Register'!$C$6:$C$27,MATCH(LARGE('Risk Register'!$N$6:$N$27,$A15),'Risk Register'!$N$6:$N$27,0)) -> Kunci jatuh ke penyerang sehingga data terenkripsi bisa dibuka | D15: =INDEX('Risk Register'!$D$6:$D$27,MATCH(LARGE('Risk Register'!$N$6:$N$27,$A15),'Risk Register'!$N$6:$N$27,0)) -> Head of Security | E15: =INDEX('Risk Register'!$J$6:$J$27,MATCH(LARGE('Risk Register'!$N$6:$N$27,$A15),'Risk Register'!$N$6:$N$27,0)) -> 12 | F15: =INDEX('Risk Register'!$K$6:$K$27,MATCH(LARGE('Risk Register'!$N$6:$N$27,$A15),'Risk Register'!$N$6:$N$27,0)) -> Tinggi | G15: =INDEX('Risk Register'!$L$6:$L$27,MATCH(LARGE('Risk Register'!$N$6:$N$27,$A15),'Risk Register'!$N$6:$N$27,0)) -> Perlu ditangani | H15: =IF(F15="Kritis","Dalam "&$D$7&" hari",IF(F15="Tinggi","Dalam "&$D$6&" hari",IF(F15="Sedang","Tinjau tiap 6 bulan","Pantau saat tinjauan berkala"))) -> Dalam 90 hari | I15: =IF(F15="Kritis","Direksi",IF(F15="Tinggi","Manajemen (risiko sisa)",IF(F15="Sedang","Pemilik risiko","Tidak perlu"))) -> Manajemen (risiko sisa)
A16: 7 | B16: =INDEX('Risk Register'!$A$6:$A$27,MATCH(LARGE('Risk Register'!$N$6:$N$27,$A16),'Risk Register'!$N$6:$N$27,0)) -> R-11 | C16: =INDEX('Risk Register'!$C$6:$C$27,MATCH(LARGE('Risk Register'!$N$6:$N$27,$A16),'Risk Register'!$N$6:$N$27,0)) -> Penyerang mengakses transaksi merchant lain | D16: =INDEX('Risk Register'!$D$6:$D$27,MATCH(LARGE('Risk Register'!$N$6:$N$27,$A16),'Risk Register'!$N$6:$N$27,0)) -> Head of Engineering | E16: =INDEX('Risk Register'!$J$6:$J$27,MATCH(LARGE('Risk Register'!$N$6:$N$27,$A16),'Risk Register'!$N$6:$N$27,0)) -> 12 | F16: =INDEX('Risk Register'!$K$6:$K$27,MATCH(LARGE('Risk Register'!$N$6:$N$27,$A16),'Risk Register'!$N$6:$N$27,0)) -> Tinggi | G16: =INDEX('Risk Register'!$L$6:$L$27,MATCH(LARGE('Risk Register'!$N$6:$N$27,$A16),'Risk Register'!$N$6:$N$27,0)) -> Perlu ditangani | H16: =IF(F16="Kritis","Dalam "&$D$7&" hari",IF(F16="Tinggi","Dalam "&$D$6&" hari",IF(F16="Sedang","Tinjau tiap 6 bulan","Pantau saat tinjauan berkala"))) -> Dalam 90 hari | I16: =IF(F16="Kritis","Direksi",IF(F16="Tinggi","Manajemen (risiko sisa)",IF(F16="Sedang","Pemilik risiko","Tidak perlu"))) -> Manajemen (risiko sisa)
A17: 8 | B17: =INDEX('Risk Register'!$A$6:$A$27,MATCH(LARGE('Risk Register'!$N$6:$N$27,$A17),'Risk Register'!$N$6:$N$27,0)) -> R-12 | C17: =INDEX('Risk Register'!$C$6:$C$27,MATCH(LARGE('Risk Register'!$N$6:$N$27,$A17),'Risk Register'!$N$6:$N$27,0)) -> Akun merchant diambil alih dan dana dialihkan | D17: =INDEX('Risk Register'!$D$6:$D$27,MATCH(LARGE('Risk Register'!$N$6:$N$27,$A17),'Risk Register'!$N$6:$N$27,0)) -> Product Owner | E17: =INDEX('Risk Register'!$J$6:$J$27,MATCH(LARGE('Risk Register'!$N$6:$N$27,$A17),'Risk Register'!$N$6:$N$27,0)) -> 12 | F17: =INDEX('Risk Register'!$K$6:$K$27,MATCH(LARGE('Risk Register'!$N$6:$N$27,$A17),'Risk Register'!$N$6:$N$27,0)) -> Tinggi | G17: =INDEX('Risk Register'!$L$6:$L$27,MATCH(LARGE('Risk Register'!$N$6:$N$27,$A17),'Risk Register'!$N$6:$N$27,0)) -> Perlu ditangani | H17: =IF(F17="Kritis","Dalam "&$D$7&" hari",IF(F17="Tinggi","Dalam "&$D$6&" hari",IF(F17="Sedang","Tinjau tiap 6 bulan","Pantau saat tinjauan berkala"))) -> Dalam 90 hari | I17: =IF(F17="Kritis","Direksi",IF(F17="Tinggi","Manajemen (risiko sisa)",IF(F17="Sedang","Pemilik risiko","Tidak perlu"))) -> Manajemen (risiko sisa)
A18: 9 | B18: =INDEX('Risk Register'!$A$6:$A$27,MATCH(LARGE('Risk Register'!$N$6:$N$27,$A18),'Risk Register'!$N$6:$N$27,0)) -> R-03 | C18: =INDEX('Risk Register'!$C$6:$C$27,MATCH(LARGE('Risk Register'!$N$6:$N$27,$A18),'Risk Register'!$N$6:$N$27,0)) -> File KYC terekspos ke internet | D18: =INDEX('Risk Register'!$D$6:$D$27,MATCH(LARGE('Risk Register'!$N$6:$N$27,$A18),'Risk Register'!$N$6:$N$27,0)) -> Head of Infrastructure | E18: =INDEX('Risk Register'!$J$6:$J$27,MATCH(LARGE('Risk Register'!$N$6:$N$27,$A18),'Risk Register'!$N$6:$N$27,0)) -> 10 | F18: =INDEX('Risk Register'!$K$6:$K$27,MATCH(LARGE('Risk Register'!$N$6:$N$27,$A18),'Risk Register'!$N$6:$N$27,0)) -> Tinggi | G18: =INDEX('Risk Register'!$L$6:$L$27,MATCH(LARGE('Risk Register'!$N$6:$N$27,$A18),'Risk Register'!$N$6:$N$27,0)) -> Perlu ditangani | H18: =IF(F18="Kritis","Dalam "&$D$7&" hari",IF(F18="Tinggi","Dalam "&$D$6&" hari",IF(F18="Sedang","Tinjau tiap 6 bulan","Pantau saat tinjauan berkala"))) -> Dalam 90 hari | I18: =IF(F18="Kritis","Direksi",IF(F18="Tinggi","Manajemen (risiko sisa)",IF(F18="Sedang","Pemilik risiko","Tidak perlu"))) -> Manajemen (risiko sisa)
A19: 10 | B19: =INDEX('Risk Register'!$A$6:$A$27,MATCH(LARGE('Risk Register'!$N$6:$N$27,$A19),'Risk Register'!$N$6:$N$27,0)) -> R-04 | C19: =INDEX('Risk Register'!$C$6:$C$27,MATCH(LARGE('Risk Register'!$N$6:$N$27,$A19),'Risk Register'!$N$6:$N$27,0)) -> Saldo atau mutasi diubah tanpa terdeteksi | D19: =INDEX('Risk Register'!$D$6:$D$27,MATCH(LARGE('Risk Register'!$N$6:$N$27,$A19),'Risk Register'!$N$6:$N$27,0)) -> Head of Finance Operations | E19: =INDEX('Risk Register'!$J$6:$J$27,MATCH(LARGE('Risk Register'!$N$6:$N$27,$A19),'Risk Register'!$N$6:$N$27,0)) -> 10 | F19: =INDEX('Risk Register'!$K$6:$K$27,MATCH(LARGE('Risk Register'!$N$6:$N$27,$A19),'Risk Register'!$N$6:$N$27,0)) -> Tinggi | G19: =INDEX('Risk Register'!$L$6:$L$27,MATCH(LARGE('Risk Register'!$N$6:$N$27,$A19),'Risk Register'!$N$6:$N$27,0)) -> Perlu ditangani | H19: =IF(F19="Kritis","Dalam "&$D$7&" hari",IF(F19="Tinggi","Dalam "&$D$6&" hari",IF(F19="Sedang","Tinjau tiap 6 bulan","Pantau saat tinjauan berkala"))) -> Dalam 90 hari | I19: =IF(F19="Kritis","Direksi",IF(F19="Tinggi","Manajemen (risiko sisa)",IF(F19="Sedang","Pemilik risiko","Tidak perlu"))) -> Manajemen (risiko sisa)
A20: 11 | B20: =INDEX('Risk Register'!$A$6:$A$27,MATCH(LARGE('Risk Register'!$N$6:$N$27,$A20),'Risk Register'!$N$6:$N$27,0)) -> R-15 | C20: =INDEX('Risk Register'!$C$6:$C$27,MATCH(LARGE('Risk Register'!$N$6:$N$27,$A20),'Risk Register'!$N$6:$N$27,0)) -> Data produksi terenkripsi dan backup ikut rusak | D20: =INDEX('Risk Register'!$D$6:$D$27,MATCH(LARGE('Risk Register'!$N$6:$N$27,$A20),'Risk Register'!$N$6:$N$27,0)) -> Head of Infrastructure | E20: =INDEX('Risk Register'!$J$6:$J$27,MATCH(LARGE('Risk Register'!$N$6:$N$27,$A20),'Risk Register'!$N$6:$N$27,0)) -> 10 | F20: =INDEX('Risk Register'!$K$6:$K$27,MATCH(LARGE('Risk Register'!$N$6:$N$27,$A20),'Risk Register'!$N$6:$N$27,0)) -> Tinggi | G20: =INDEX('Risk Register'!$L$6:$L$27,MATCH(LARGE('Risk Register'!$N$6:$N$27,$A20),'Risk Register'!$N$6:$N$27,0)) -> Perlu ditangani | H20: =IF(F20="Kritis","Dalam "&$D$7&" hari",IF(F20="Tinggi","Dalam "&$D$6&" hari",IF(F20="Sedang","Tinjau tiap 6 bulan","Pantau saat tinjauan berkala"))) -> Dalam 90 hari | I20: =IF(F20="Kritis","Direksi",IF(F20="Tinggi","Manajemen (risiko sisa)",IF(F20="Sedang","Pemilik risiko","Tidak perlu"))) -> Manajemen (risiko sisa)
A21: 12 | B21: =INDEX('Risk Register'!$A$6:$A$27,MATCH(LARGE('Risk Register'!$N$6:$N$27,$A21),'Risk Register'!$N$6:$N$27,0)) -> R-20 | C21: =INDEX('Risk Register'!$C$6:$C$27,MATCH(LARGE('Risk Register'!$N$6:$N$27,$A21),'Risk Register'!$N$6:$N$27,0)) -> Data KYC pengguna bocor dari penyedia | D21: =INDEX('Risk Register'!$D$6:$D$27,MATCH(LARGE('Risk Register'!$N$6:$N$27,$A21),'Risk Register'!$N$6:$N$27,0)) -> Compliance Officer | E21: =INDEX('Risk Register'!$J$6:$J$27,MATCH(LARGE('Risk Register'!$N$6:$N$27,$A21),'Risk Register'!$N$6:$N$27,0)) -> 10 | F21: =INDEX('Risk Register'!$K$6:$K$27,MATCH(LARGE('Risk Register'!$N$6:$N$27,$A21),'Risk Register'!$N$6:$N$27,0)) -> Tinggi | G21: =INDEX('Risk Register'!$L$6:$L$27,MATCH(LARGE('Risk Register'!$N$6:$N$27,$A21),'Risk Register'!$N$6:$N$27,0)) -> Perlu ditangani | H21: =IF(F21="Kritis","Dalam "&$D$7&" hari",IF(F21="Tinggi","Dalam "&$D$6&" hari",IF(F21="Sedang","Tinjau tiap 6 bulan","Pantau saat tinjauan berkala"))) -> Dalam 90 hari | I21: =IF(F21="Kritis","Direksi",IF(F21="Tinggi","Manajemen (risiko sisa)",IF(F21="Sedang","Pemilik risiko","Tidak perlu"))) -> Manajemen (risiko sisa)
... A31: 22 | B31: =INDEX('Risk Register'!$A$6:$A$27,MATCH(LARGE('Risk Register'!$N$6:$N$27,$A31),'Risk Register'!$N$6:$N$27,0)) -> R-08 | C31: =INDEX('Risk Register'!$C$6:$C$27,MATCH(LARGE('Risk Register'!$N$6:$N$27,$A31),'Risk Register'!$N$6:$N$27,0)) -> Kebijakan usang atau berubah tanpa persetujuan, kewajiban hukum terlewat | D31: =INDEX('Risk Register'!$D$6:$D$27,MATCH(LARGE('Risk Register'!$N$6:$N$27,$A31),'Risk Register'!$N$6:$N$27,0)) -> Compliance Officer | E31: =INDEX('Risk Register'!$J$6:$J$27,MATCH(LARGE('Risk Register'!$N$6:$N$27,$A31),'Risk Register'!$N$6:$N$27,0)) -> 6 | F31: =INDEX('Risk Register'!$K$6:$K$27,MATCH(LARGE('Risk Register'!$N$6:$N$27,$A31),'Risk Register'!$N$6:$N$27,0)) -> Sedang | G31: =INDEX('Risk Register'!$L$6:$L$27,MATCH(LARGE('Risk Register'!$N$6:$N$27,$A31),'Risk Register'!$N$6:$N$27,0)) -> Dapat diterima, perlu persetujuan pemilik risiko | H31: =IF(F31="Kritis","Dalam "&$D$7&" hari",IF(F31="Tinggi","Dalam "&$D$6&" hari",IF(F31="Sedang","Tinjau tiap 6 bulan","Pantau saat tinjauan berkala"))) -> Tinjau tiap 6 bulan | I31: =IF(F31="Kritis","Direksi",IF(F31="Tinggi","Manajemen (risiko sisa)",IF(F31="Sedang","Pemilik risiko","Tidak perlu"))) -> Pemilik risiko
A33: Catatan: batas penerimaan ada di sheet Kriteria (skor 9). Tenggat 90 dan 30 hari adalah parameter rekaan untuk LumiPay.

Sheet Penanganan
A1: Rencana Penanganan Risiko LumiPay v1.0 (14 Okt 2026) (langkah 5)
A2: Untuk tiap risiko dipilih opsi penanganan (mitigasi, terima, hindari, atau transfer), kontrol Annex A 2022, dan diperkirakan risiko sisa setelah kontrol diterapkan.
A3: Risiko dengan akar masalah sama ditangani bersama dalam satu kelompok (lihat sheet Kelompok). Kontrol di sini menjadi bahan untuk SoA (langkah 6).
A4: Legenda: sel biru berlatar kuning = nilai yang diisi (tanggal, nilai kemungkinan dan dampak risiko sisa). Kolom lain berisi rumus atau teks usulan.
A6: Tanggal penetapan rencana | D6: 46307
A9: ID | B9: Kelompok | C9: Skenario risiko | D9: Skor awal | E9: Level awal | F9: Prioritas evaluasi | G9: Opsi penanganan | H9: Kontrol Annex A (2022) | I9: Tindakan penanganan | J9: Alasan pemilihan opsi | K9: Penanggung jawab | L9: Target selesai atau tinjau | M9: Kemungkinan sisa (1-5) | N9: Dampak sisa (1-5) | O9: Skor sisa | P9: Level sisa | Q9: Status risiko sisa | R9: Penyetuju risiko sisa
A10: R-01 | B10: G3 | C10: =INDEX('Risk Register'!$C$6:$C$27,MATCH($A10,'Risk Register'!$A$6:$A$27,0)) -> Data transaksi dicuri atau dimanipulasi lewat celah aplikasi | D10: =INDEX('Risk Register'!$J$6:$J$27,MATCH($A10,'Risk Register'!$A$6:$A$27,0)) -> 12 | E10: =INDEX('Risk Register'!$K$6:$K$27,MATCH($A10,'Risk Register'!$A$6:$A$27,0)) -> Tinggi | F10: =MATCH($A10,Evaluasi!$B$10:$B$31,0) -> 4 | G10: Mitigasi | H10: 8.26, 8.28, 8.29, 8.8 | I10: Validasi input dan query berparameter pada semua akses database; code review dan pengujian keamanan (SAST dan pentest) sebelum rilis; patch kerentanan kritis maksimal 14 hari. | J10: Skor 12 di atas batas; kontrol pencegahan di tingkat kode paling efektif menurunkan kemungkinan. | K10: =INDEX('Risk Register'!$D$6:$D$27,MATCH($A10,'Risk Register'!$A$6:$A$27,0)) -> Head of Engineering | L10: =IF(G10="Terima",EDATE($D$6,6),$D$6+Evaluasi!$D$6) -> 46397 | M10: 2 | N10: 4 | O10: =M10*N10 -> 8 | P10: =IF(O10<=Kriteria!$B$3,"Rendah",IF(O10<=Kriteria!$B$4,"Sedang",IF(O10<=Kriteria!$B$5,"Tinggi","Kritis"))) -> Sedang | Q10: =IF(O10>Kriteria!$B$6,"Perlu penanganan lanjutan","Dapat diterima") -> Dapat diterima | R10: =IF(E10="Kritis","Direksi",IF(E10="Tinggi","Manajemen",IF(E10="Sedang","Pemilik risiko","Tidak perlu"))) -> Manajemen
A11: R-02 | B11: G1 | C11: =INDEX('Risk Register'!$C$6:$C$27,MATCH($A11,'Risk Register'!$A$6:$A$27,0)) -> Data KTP dan swafoto pengguna bocor atau disalahgunakan | D11: =INDEX('Risk Register'!$J$6:$J$27,MATCH($A11,'Risk Register'!$A$6:$A$27,0)) -> 12 | E11: =INDEX('Risk Register'!$K$6:$K$27,MATCH($A11,'Risk Register'!$A$6:$A$27,0)) -> Tinggi | F11: =MATCH($A11,Evaluasi!$B$10:$B$31,0) -> 5 | G11: Mitigasi | H11: 5.15, 5.18, 8.2, 8.3, 8.5, 8.15 | I11: Hak akses berbasis peran (least privilege) ke data KYC, MFA wajib untuk semua akses, tinjauan hak akses tiap 3 bulan, log akses data KYC dipantau. | J11: Skor 12 di atas batas; membatasi siapa yang bisa mengakses menurunkan kemungkinan, dampak data bocor tetap besar. | K11: =INDEX('Risk Register'!$D$6:$D$27,MATCH($A11,'Risk Register'!$A$6:$A$27,0)) -> Compliance Officer | L11: =IF(G11="Terima",EDATE($D$6,6),$D$6+Evaluasi!$D$6) -> 46397 | M11: 2 | N11: 4 | O11: =M11*N11 -> 8 | P11: =IF(O11<=Kriteria!$B$3,"Rendah",IF(O11<=Kriteria!$B$4,"Sedang",IF(O11<=Kriteria!$B$5,"Tinggi","Kritis"))) -> Sedang | Q11: =IF(O11>Kriteria!$B$6,"Perlu penanganan lanjutan","Dapat diterima") -> Dapat diterima | R11: =IF(E11="Kritis","Direksi",IF(E11="Tinggi","Manajemen",IF(E11="Sedang","Pemilik risiko","Tidak perlu"))) -> Manajemen
A12: R-03 | B12: G5 | C12: =INDEX('Risk Register'!$C$6:$C$27,MATCH($A12,'Risk Register'!$A$6:$A$27,0)) -> File KYC terekspos ke internet | D12: =INDEX('Risk Register'!$J$6:$J$27,MATCH($A12,'Risk Register'!$A$6:$A$27,0)) -> 10 | E12: =INDEX('Risk Register'!$K$6:$K$27,MATCH($A12,'Risk Register'!$A$6:$A$27,0)) -> Tinggi | F12: =MATCH($A12,Evaluasi!$B$10:$B$31,0) -> 9 | G12: Mitigasi | H12: 8.9, 8.3, 8.24, 8.16, 5.23 | I12: Blok akses publik pada object storage secara default, enkripsi at-rest, baseline konfigurasi cloud dengan pemindaian otomatis dan alert jika ada perubahan. | J12: Skor 10 di atas batas; konfigurasi yang dijaga otomatis hampir menutup kemungkinan salah konfigurasi. | K12: =INDEX('Risk Register'!$D$6:$D$27,MATCH($A12,'Risk Register'!$A$6:$A$27,0)) -> Head of Infrastructure | L12: =IF(G12="Terima",EDATE($D$6,6),$D$6+Evaluasi!$D$6) -> 46397 | M12: 1 | N12: 5 | O12: =M12*N12 -> 5 | P12: =IF(O12<=Kriteria!$B$3,"Rendah",IF(O12<=Kriteria!$B$4,"Sedang",IF(O12<=Kriteria!$B$5,"Tinggi","Kritis"))) -> Sedang | Q12: =IF(O12>Kriteria!$B$6,"Perlu penanganan lanjutan","Dapat diterima") -> Dapat diterima | R12: =IF(E12="Kritis","Direksi",IF(E12="Tinggi","Manajemen",IF(E12="Sedang","Pemilik risiko","Tidak perlu"))) -> Manajemen
A13: R-04 | B13: G1 | C13: =INDEX('Risk Register'!$C$6:$C$27,MATCH($A13,'Risk Register'!$A$6:$A$27,0)) -> Saldo atau mutasi diubah tanpa terdeteksi | D13: =INDEX('Risk Register'!$J$6:$J$27,MATCH($A13,'Risk Register'!$A$6:$A$27,0)) -> 10 | E13: =INDEX('Risk Register'!$K$6:$K$27,MATCH($A13,'Risk Register'!$A$6:$A$27,0)) -> Tinggi | F13: =MATCH($A13,Evaluasi!$B$10:$B$31,0) -> 10 | G13: Mitigasi | H13: 5.3, 8.3, 8.2, 8.15 | I13: Pemisahan tugas antara pengubah dan penyetuju data ledger, rekonsiliasi otomatis harian, log perubahan ledger yang tidak bisa diubah. | J13: Skor 10 di atas batas; dampak finansial tetap besar jika terjadi, jadi yang ditekan adalah kemungkinan dan deteksi. | K13: =INDEX('Risk Register'!$D$6:$D$27,MATCH($A13,'Risk Register'!$A$6:$A$27,0)) -> Head of Finance Operations | L13: =IF(G13="Terima",EDATE($D$6,6),$D$6+Evaluasi!$D$6) -> 46397 | M13: 1 | N13: 5 | O13: =M13*N13 -> 5 | P13: =IF(O13<=Kriteria!$B$3,"Rendah",IF(O13<=Kriteria!$B$4,"Sedang",IF(O13<=Kriteria!$B$5,"Tinggi","Kritis"))) -> Sedang | Q13: =IF(O13>Kriteria!$B$6,"Perlu penanganan lanjutan","Dapat diterima") -> Dapat diterima | R13: =IF(E13="Kritis","Direksi",IF(E13="Tinggi","Manajemen",IF(E13="Sedang","Pemilik risiko","Tidak perlu"))) -> Manajemen
A14: R-05 | B14: G2 | C14: =INDEX('Risk Register'!$C$6:$C$27,MATCH($A14,'Risk Register'!$A$6:$A$27,0)) -> Kunci jatuh ke penyerang sehingga data terenkripsi bisa dibuka | D14: =INDEX('Risk Register'!$J$6:$J$27,MATCH($A14,'Risk Register'!$A$6:$A$27,0)) -> 12 | E14: =INDEX('Risk Register'!$K$6:$K$27,MATCH($A14,'Risk Register'!$A$6:$A$27,0)) -> Tinggi | F14: =MATCH($A14,Evaluasi!$B$10:$B$31,0) -> 6 | G14: Mitigasi | H14: 8.24, 5.17, 8.28, 8.4 | I14: Semua secret dipindah ke secrets manager, secret scanning di repositori dan pipeline, rotasi kunci terjadwal, larangan menyimpan secret di kode dan chat. | J14: Skor 12 di atas batas; akar masalah (secret di kode) dihilangkan, dampak kebocoran kunci tetap serius. | K14: =INDEX('Risk Register'!$D$6:$D$27,MATCH($A14,'Risk Register'!$A$6:$A$27,0)) -> Head of Security | L14: =IF(G14="Terima",EDATE($D$6,6),$D$6+Evaluasi!$D$6) -> 46397 | M14: 2 | N14: 4 | O14: =M14*N14 -> 8 | P14: =IF(O14<=Kriteria!$B$3,"Rendah",IF(O14<=Kriteria!$B$4,"Sedang",IF(O14<=Kriteria!$B$5,"Tinggi","Kritis"))) -> Sedang | Q14: =IF(O14>Kriteria!$B$6,"Perlu penanganan lanjutan","Dapat diterima") -> Dapat diterima | R14: =IF(E14="Kritis","Direksi",IF(E14="Tinggi","Manajemen",IF(E14="Sedang","Pemilik risiko","Tidak perlu"))) -> Manajemen
A15: R-06 | B15: G2 | C15: =INDEX('Risk Register'!$C$6:$C$27,MATCH($A15,'Risk Register'!$A$6:$A$27,0)) -> Kode sumber bocor sehingga celah aplikasi dan logika bisnis terlihat pihak yang tidak berwenang | D15: =INDEX('Risk Register'!$J$6:$J$27,MATCH($A15,'Risk Register'!$A$6:$A$27,0)) -> 9 | E15: =INDEX('Risk Register'!$K$6:$K$27,MATCH($A15,'Risk Register'!$A$6:$A$27,0)) -> Sedang | F15: =MATCH($A15,Evaluasi!$B$10:$B$31,0) -> 13 | G15: Mitigasi | H15: 8.4, 5.18, 8.5, 8.3 | I15: Repositori privat secara default dengan kontrol publikasi, MFA wajib, pencabutan akun mantan karyawan, tinjauan akses repositori tiap 3 bulan. | J15: Skor 9 sebenarnya boleh diterima, tetapi kontrolnya sama dengan R-05 dan R-07 sehingga ditangani bersama dalam satu kelompok. | K15: =INDEX('Risk Register'!$D$6:$D$27,MATCH($A15,'Risk Register'!$A$6:$A$27,0)) -> Head of Engineering | L15: =IF(G15="Terima",EDATE($D$6,6),$D$6+Evaluasi!$D$6) -> 46397 | M15: 2 | N15: 3 | O15: =M15*N15 -> 6 | P15: =IF(O15<=Kriteria!$B$3,"Rendah",IF(O15<=Kriteria!$B$4,"Sedang",IF(O15<=Kriteria!$B$5,"Tinggi","Kritis"))) -> Sedang | Q15: =IF(O15>Kriteria!$B$6,"Perlu penanganan lanjutan","Dapat diterima") -> Dapat diterima | R15: =IF(E15="Kritis","Direksi",IF(E15="Tinggi","Manajemen",IF(E15="Sedang","Pemilik risiko","Tidak perlu"))) -> Pemilik risiko
A16: R-07 | B16: G2 | C16: =INDEX('Risk Register'!$C$6:$C$27,MATCH($A16,'Risk Register'!$A$6:$A$27,0)) -> Kode atau pipeline diubah tanpa izin sehingga kode berbahaya masuk ke produksi dan dana atau data pengguna disalahgunakan | D16: =INDEX('Risk Register'!$J$6:$J$27,MATCH($A16,'Risk Register'!$A$6:$A$27,0)) -> 15 | E16: =INDEX('Risk Register'!$K$6:$K$27,MATCH($A16,'Risk Register'!$A$6:$A$27,0)) -> Tinggi | F16: =MATCH($A16,Evaluasi!$B$10:$B$31,0) -> 3 | G16: Mitigasi | H16: 8.4, 8.32, 5.18, 8.5, 8.25 | I16: Branch protection dan review kode wajib dua orang, deploy ke produksi lewat persetujuan, MFA wajib pada repositori dan pipeline, pencabutan akun lama, pemantauan perubahan pipeline. | J16: Skor 15 di atas batas; akibat tetap berat jika lolos, jadi dibutuhkan lapisan persetujuan deploy dan deteksi agar dampak sisa turun. | K16: =INDEX('Risk Register'!$D$6:$D$27,MATCH($A16,'Risk Register'!$A$6:$A$27,0)) -> Head of Engineering | L16: =IF(G16="Terima",EDATE($D$6,6),$D$6+Evaluasi!$D$6) -> 46397 | M16: 2 | N16: 4 | O16: =M16*N16 -> 8 | P16: =IF(O16<=Kriteria!$B$3,"Rendah",IF(O16<=Kriteria!$B$4,"Sedang",IF(O16<=Kriteria!$B$5,"Tinggi","Kritis"))) -> Sedang | Q16: =IF(O16>Kriteria!$B$6,"Perlu penanganan lanjutan","Dapat diterima") -> Dapat diterima | R16: =IF(E16="Kritis","Direksi",IF(E16="Tinggi","Manajemen",IF(E16="Sedang","Pemilik risiko","Tidak perlu"))) -> Manajemen
A17: R-08 | B17: - | C17: =INDEX('Risk Register'!$C$6:$C$27,MATCH($A17,'Risk Register'!$A$6:$A$27,0)) -> Kebijakan usang atau berubah tanpa persetujuan, kewajiban hukum terlewat | D17: =INDEX('Risk Register'!$J$6:$J$27,MATCH($A17,'Risk Register'!$A$6:$A$27,0)) -> 6 | E17: =INDEX('Risk Register'!$K$6:$K$27,MATCH($A17,'Risk Register'!$A$6:$A$27,0)) -> Sedang | F17: =MATCH($A17,Evaluasi!$B$10:$B$31,0) -> 22 | G17: Terima | H17: - | I17: Dipantau pada tinjauan berkala 6 bulan. | J17: Skor 6, di bawah batas penerimaan; dampak operasional kecil. | K17: =INDEX('Risk Register'!$D$6:$D$27,MATCH($A17,'Risk Register'!$A$6:$A$27,0)) -> Compliance Officer | L17: =IF(G17="Terima",EDATE($D$6,6),$D$6+Evaluasi!$D$6) -> 46489 | M17: =INDEX('Risk Register'!$E$6:$E$27,MATCH($A17,'Risk Register'!$A$6:$A$27,0)) -> 3 | N17: =INDEX('Risk Register'!$I$6:$I$27,MATCH($A17,'Risk Register'!$A$6:$A$27,0)) -> 2 | O17: =M17*N17 -> 6 | P17: =IF(O17<=Kriteria!$B$3,"Rendah",IF(O17<=Kriteria!$B$4,"Sedang",IF(O17<=Kriteria!$B$5,"Tinggi","Kritis"))) -> Sedang | Q17: =IF(O17>Kriteria!$B$6,"Perlu penanganan lanjutan","Dapat diterima") -> Dapat diterima | R17: =IF(E17="Kritis","Direksi",IF(E17="Tinggi","Manajemen",IF(E17="Sedang","Pemilik risiko","Tidak perlu"))) -> Pemilik risiko
A18: R-09 | B18: - | C18: =INDEX('Risk Register'!$C$6:$C$27,MATCH($A18,'Risk Register'!$A$6:$A$27,0)) -> Aplikasi palsu mencuri kredensial pengguna | D18: =INDEX('Risk Register'!$J$6:$J$27,MATCH($A18,'Risk Register'!$A$6:$A$27,0)) -> 9 | E18: =INDEX('Risk Register'!$K$6:$K$27,MATCH($A18,'Risk Register'!$A$6:$A$27,0)) -> Sedang | F18: =MATCH($A18,Evaluasi!$B$10:$B$31,0) -> 14 | G18: Terima | H18: - | I18: Dipantau pada tinjauan berkala 6 bulan; laporan pengguna soal aplikasi tiruan ditindaklanjuti. | J18: Skor 9, tepat di batas penerimaan; ditinjau tiap 6 bulan. | K18: =INDEX('Risk Register'!$D$6:$D$27,MATCH($A18,'Risk Register'!$A$6:$A$27,0)) -> Product Owner | L18: =IF(G18="Terima",EDATE($D$6,6),$D$6+Evaluasi!$D$6) -> 46489 | M18: =INDEX('Risk Register'!$E$6:$E$27,MATCH($A18,'Risk Register'!$A$6:$A$27,0)) -> 3 | N18: =INDEX('Risk Register'!$I$6:$I$27,MATCH($A18,'Risk Register'!$A$6:$A$27,0)) -> 3 | O18: =M18*N18 -> 9 | P18: =IF(O18<=Kriteria!$B$3,"Rendah",IF(O18<=Kriteria!$B$4,"Sedang",IF(O18<=Kriteria!$B$5,"Tinggi","Kritis"))) -> Sedang | Q18: =IF(O18>Kriteria!$B$6,"Perlu penanganan lanjutan","Dapat diterima") -> Dapat diterima | R18: =IF(E18="Kritis","Direksi",IF(E18="Tinggi","Manajemen",IF(E18="Sedang","Pemilik risiko","Tidak perlu"))) -> Pemilik risiko
A19: R-10 | B19: G4 | C19: =INDEX('Risk Register'!$C$6:$C$27,MATCH($A19,'Risk Register'!$A$6:$A$27,0)) -> API tidak tersedia, transaksi merchant gagal | D19: =INDEX('Risk Register'!$J$6:$J$27,MATCH($A19,'Risk Register'!$A$6:$A$27,0)) -> 16 | E19: =INDEX('Risk Register'!$K$6:$K$27,MATCH($A19,'Risk Register'!$A$6:$A$27,0)) -> Tinggi | F19: =MATCH($A19,Evaluasi!$B$10:$B$31,0) -> 1 | G19: Mitigasi | H19: 8.6, 8.20, 8.21, 8.16 | I19: Rate limiting pada API, layanan proteksi DDoS dari penyedia cloud atau CDN, autoscaling dan pemantauan lonjakan trafik. | J19: Skor 16 tertinggi; serangan DDoS tidak bisa dicegah sepenuhnya, jadi tujuannya memperkecil frekuensi berhasil dan durasi gangguan. | K19: =INDEX('Risk Register'!$D$6:$D$27,MATCH($A19,'Risk Register'!$A$6:$A$27,0)) -> Head of Engineering | L19: =IF(G19="Terima",EDATE($D$6,6),$D$6+Evaluasi!$D$6) -> 46397 | M19: 2 | N19: 3 | O19: =M19*N19 -> 6 | P19: =IF(O19<=Kriteria!$B$3,"Rendah",IF(O19<=Kriteria!$B$4,"Sedang",IF(O19<=Kriteria!$B$5,"Tinggi","Kritis"))) -> Sedang | Q19: =IF(O19>Kriteria!$B$6,"Perlu penanganan lanjutan","Dapat diterima") -> Dapat diterima | R19: =IF(E19="Kritis","Direksi",IF(E19="Tinggi","Manajemen",IF(E19="Sedang","Pemilik risiko","Tidak perlu"))) -> Manajemen
A20: R-11 | B20: G3 | C20: =INDEX('Risk Register'!$C$6:$C$27,MATCH($A20,'Risk Register'!$A$6:$A$27,0)) -> Penyerang mengakses transaksi merchant lain | D20: =INDEX('Risk Register'!$J$6:$J$27,MATCH($A20,'Risk Register'!$A$6:$A$27,0)) -> 12 | E20: =INDEX('Risk Register'!$K$6:$K$27,MATCH($A20,'Risk Register'!$A$6:$A$27,0)) -> Tinggi | F20: =MATCH($A20,Evaluasi!$B$10:$B$31,0) -> 7 | G20: Mitigasi | H20: 8.26, 8.28, 8.29, 8.3, 8.16 | I20: Otorisasi per objek diuji di setiap endpoint, pentest API berkala, pemantauan pola akses tidak wajar. | J20: Skor 12 di atas batas; celah otorisasi ditutup di kode dan diuji berkala. | K20: =INDEX('Risk Register'!$D$6:$D$27,MATCH($A20,'Risk Register'!$A$6:$A$27,0)) -> Head of Engineering | L20: =IF(G20="Terima",EDATE($D$6,6),$D$6+Evaluasi!$D$6) -> 46397 | M20: 2 | N20: 4 | O20: =M20*N20 -> 8 | P20: =IF(O20<=Kriteria!$B$3,"Rendah",IF(O20<=Kriteria!$B$4,"Sedang",IF(O20<=Kriteria!$B$5,"Tinggi","Kritis"))) -> Sedang | Q20: =IF(O20>Kriteria!$B$6,"Perlu penanganan lanjutan","Dapat diterima") -> Dapat diterima | R20: =IF(E20="Kritis","Direksi",IF(E20="Tinggi","Manajemen",IF(E20="Sedang","Pemilik risiko","Tidak perlu"))) -> Manajemen
A21: R-12 | B21: G1 | C21: =INDEX('Risk Register'!$C$6:$C$27,MATCH($A21,'Risk Register'!$A$6:$A$27,0)) -> Akun merchant diambil alih dan dana dialihkan | D21: =INDEX('Risk Register'!$J$6:$J$27,MATCH($A21,'Risk Register'!$A$6:$A$27,0)) -> 12 | E21: =INDEX('Risk Register'!$K$6:$K$27,MATCH($A21,'Risk Register'!$A$6:$A$27,0)) -> Tinggi | F21: =MATCH($A21,Evaluasi!$B$10:$B$31,0) -> 8 | G21: Mitigasi | H21: 8.5, 5.17, 8.16 | I21: MFA wajib untuk akun merchant, kebijakan kata sandi dan pengecekan kata sandi bocor, deteksi login anomali dan pembatasan percobaan. | J21: Skor 12 di atas batas; MFA langsung memutus credential stuffing. | K21: =INDEX('Risk Register'!$D$6:$D$27,MATCH($A21,'Risk Register'!$A$6:$A$27,0)) -> Product Owner | L21: =IF(G21="Terima",EDATE($D$6,6),$D$6+Evaluasi!$D$6) -> 46397 | M21: 2 | N21: 3 | O21: =M21*N21 -> 6 | P21: =IF(O21<=Kriteria!$B$3,"Rendah",IF(O21<=Kriteria!$B$4,"Sedang",IF(O21<=Kriteria!$B$5,"Tinggi","Kritis"))) -> Sedang | Q21: =IF(O21>Kriteria!$B$6,"Perlu penanganan lanjutan","Dapat diterima") -> Dapat diterima | R21: =IF(E21="Kritis","Direksi",IF(E21="Tinggi","Manajemen",IF(E21="Sedang","Pemilik risiko","Tidak perlu"))) -> Manajemen
A22: R-13 | B22: G7 | C22: =INDEX('Risk Register'!$C$6:$C$27,MATCH($A22,'Risk Register'!$A$6:$A$27,0)) -> Insiden tidak terdeteksi atau tidak bisa diselidiki | D22: =INDEX('Risk Register'!$J$6:$J$27,MATCH($A22,'Risk Register'!$A$6:$A$27,0)) -> 9 | E22: =INDEX('Risk Register'!$K$6:$K$27,MATCH($A22,'Risk Register'!$A$6:$A$27,0)) -> Sedang | F22: =MATCH($A22,Evaluasi!$B$10:$B$31,0) -> 15 | G22: Mitigasi | H22: 8.15, 8.16 | I22: Retensi log minimal 12 bulan, perlindungan integritas log, alerting untuk kejadian kritis. | J22: Skor 9 boleh diterima, tetapi kontrol deteksi di kelompok lain (R-02, R-04, R-10, R-11) bergantung pada log yang memadai. | K22: =INDEX('Risk Register'!$D$6:$D$27,MATCH($A22,'Risk Register'!$A$6:$A$27,0)) -> Head of Security | L22: =IF(G22="Terima",EDATE($D$6,6),$D$6+Evaluasi!$D$6) -> 46397 | M22: 2 | N22: 3 | O22: =M22*N22 -> 6 | P22: =IF(O22<=Kriteria!$B$3,"Rendah",IF(O22<=Kriteria!$B$4,"Sedang",IF(O22<=Kriteria!$B$5,"Tinggi","Kritis"))) -> Sedang | Q22: =IF(O22>Kriteria!$B$6,"Perlu penanganan lanjutan","Dapat diterima") -> Dapat diterima | R22: =IF(E22="Kritis","Direksi",IF(E22="Tinggi","Manajemen",IF(E22="Sedang","Pemilik risiko","Tidak perlu"))) -> Pemilik risiko
A23: R-14 | B23: - | C23: =INDEX('Risk Register'!$C$6:$C$27,MATCH($A23,'Risk Register'!$A$6:$A$27,0)) -> Layanan berhenti berjam-jam | D23: =INDEX('Risk Register'!$J$6:$J$27,MATCH($A23,'Risk Register'!$A$6:$A$27,0)) -> 8 | E23: =INDEX('Risk Register'!$K$6:$K$27,MATCH($A23,'Risk Register'!$A$6:$A$27,0)) -> Sedang | F23: =MATCH($A23,Evaluasi!$B$10:$B$31,0) -> 19 | G23: Terima | H23: - | I23: Dipantau pada tinjauan berkala 6 bulan. | J23: Skor 8; gangguan penyedia cloud ditoleransi sesuai SLA penyedia. | K23: =INDEX('Risk Register'!$D$6:$D$27,MATCH($A23,'Risk Register'!$A$6:$A$27,0)) -> Head of Infrastructure | L23: =IF(G23="Terima",EDATE($D$6,6),$D$6+Evaluasi!$D$6) -> 46489 | M23: =INDEX('Risk Register'!$E$6:$E$27,MATCH($A23,'Risk Register'!$A$6:$A$27,0)) -> 2 | N23: =INDEX('Risk Register'!$I$6:$I$27,MATCH($A23,'Risk Register'!$A$6:$A$27,0)) -> 4 | O23: =M23*N23 -> 8 | P23: =IF(O23<=Kriteria!$B$3,"Rendah",IF(O23<=Kriteria!$B$4,"Sedang",IF(O23<=Kriteria!$B$5,"Tinggi","Kritis"))) -> Sedang | Q23: =IF(O23>Kriteria!$B$6,"Perlu penanganan lanjutan","Dapat diterima") -> Dapat diterima | R23: =IF(E23="Kritis","Direksi",IF(E23="Tinggi","Manajemen",IF(E23="Sedang","Pemilik risiko","Tidak perlu"))) -> Pemilik risiko
A24: R-15 | B24: G4 | C24: =INDEX('Risk Register'!$C$6:$C$27,MATCH($A24,'Risk Register'!$A$6:$A$27,0)) -> Data produksi terenkripsi dan backup ikut rusak | D24: =INDEX('Risk Register'!$J$6:$J$27,MATCH($A24,'Risk Register'!$A$6:$A$27,0)) -> 10 | E24: =INDEX('Risk Register'!$K$6:$K$27,MATCH($A24,'Risk Register'!$A$6:$A$27,0)) -> Tinggi | F24: =MATCH($A24,Evaluasi!$B$10:$B$31,0) -> 11 | G24: Mitigasi dan transfer | H24: 8.13, 8.7, 5.30, 8.14, 5.29 | I24: Backup terisolasi (immutable) dengan uji pemulihan berkala, proteksi endpoint dan server, rencana pemulihan dengan target waktu; sebagian risiko dialihkan lewat asuransi siber. | J24: Skor 10 di atas batas; backup teruji menurunkan dampak, asuransi mengalihkan sebagian kerugian finansial. | K24: =INDEX('Risk Register'!$D$6:$D$27,MATCH($A24,'Risk Register'!$A$6:$A$27,0)) -> Head of Infrastructure | L24: =IF(G24="Terima",EDATE($D$6,6),$D$6+Evaluasi!$D$6) -> 46397 | M24: 2 | N24: 3 | O24: =M24*N24 -> 6 | P24: =IF(O24<=Kriteria!$B$3,"Rendah",IF(O24<=Kriteria!$B$4,"Sedang",IF(O24<=Kriteria!$B$5,"Tinggi","Kritis"))) -> Sedang | Q24: =IF(O24>Kriteria!$B$6,"Perlu penanganan lanjutan","Dapat diterima") -> Dapat diterima | R24: =IF(E24="Kritis","Direksi",IF(E24="Tinggi","Manajemen",IF(E24="Sedang","Pemilik risiko","Tidak perlu"))) -> Manajemen
A25: R-16 | B25: - | C25: =INDEX('Risk Register'!$C$6:$C$27,MATCH($A25,'Risk Register'!$A$6:$A$27,0)) -> Penyerang di jaringan kantor menjangkau sistem internal | D25: =INDEX('Risk Register'!$J$6:$J$27,MATCH($A25,'Risk Register'!$A$6:$A$27,0)) -> 6 | E25: =INDEX('Risk Register'!$K$6:$K$27,MATCH($A25,'Risk Register'!$A$6:$A$27,0)) -> Sedang | F25: =MATCH($A25,Evaluasi!$B$10:$B$31,0) -> 21 | G25: Terima | H25: - | I25: Dipantau pada tinjauan berkala 6 bulan. | J25: Skor 6; sistem produksi berada di cloud sehingga jangkauan dari jaringan kantor terbatas. | K25: =INDEX('Risk Register'!$D$6:$D$27,MATCH($A25,'Risk Register'!$A$6:$A$27,0)) -> Head of Infrastructure | L25: =IF(G25="Terima",EDATE($D$6,6),$D$6+Evaluasi!$D$6) -> 46489 | M25: =INDEX('Risk Register'!$E$6:$E$27,MATCH($A25,'Risk Register'!$A$6:$A$27,0)) -> 2 | N25: =INDEX('Risk Register'!$I$6:$I$27,MATCH($A25,'Risk Register'!$A$6:$A$27,0)) -> 3 | O25: =M25*N25 -> 6 | P25: =IF(O25<=Kriteria!$B$3,"Rendah",IF(O25<=Kriteria!$B$4,"Sedang",IF(O25<=Kriteria!$B$5,"Tinggi","Kritis"))) -> Sedang | Q25: =IF(O25>Kriteria!$B$6,"Perlu penanganan lanjutan","Dapat diterima") -> Dapat diterima | R25: =IF(E25="Kritis","Direksi",IF(E25="Tinggi","Manajemen",IF(E25="Sedang","Pemilik risiko","Tidak perlu"))) -> Pemilik risiko
A26: R-17 | B26: - | C26: =INDEX('Risk Register'!$C$6:$C$27,MATCH($A26,'Risk Register'!$A$6:$A$27,0)) -> Data perusahaan bocor dari laptop | D26: =INDEX('Risk Register'!$J$6:$J$27,MATCH($A26,'Risk Register'!$A$6:$A$27,0)) -> 9 | E26: =INDEX('Risk Register'!$K$6:$K$27,MATCH($A26,'Risk Register'!$A$6:$A$27,0)) -> Sedang | F26: =MATCH($A26,Evaluasi!$B$10:$B$31,0) -> 16 | G26: Terima | H26: - | I26: Dipantau pada tinjauan berkala 6 bulan. | J26: Skor 9, tepat di batas penerimaan; enkripsi disk ditunda karena keterbatasan anggaran. | K26: =INDEX('Risk Register'!$D$6:$D$27,MATCH($A26,'Risk Register'!$A$6:$A$27,0)) -> Head of IT Support | L26: =IF(G26="Terima",EDATE($D$6,6),$D$6+Evaluasi!$D$6) -> 46489 | M26: =INDEX('Risk Register'!$E$6:$E$27,MATCH($A26,'Risk Register'!$A$6:$A$27,0)) -> 3 | N26: =INDEX('Risk Register'!$I$6:$I$27,MATCH($A26,'Risk Register'!$A$6:$A$27,0)) -> 3 | O26: =M26*N26 -> 9 | P26: =IF(O26<=Kriteria!$B$3,"Rendah",IF(O26<=Kriteria!$B$4,"Sedang",IF(O26<=Kriteria!$B$5,"Tinggi","Kritis"))) -> Sedang | Q26: =IF(O26>Kriteria!$B$6,"Perlu penanganan lanjutan","Dapat diterima") -> Dapat diterima | R26: =IF(E26="Kritis","Direksi",IF(E26="Tinggi","Manajemen",IF(E26="Sedang","Pemilik risiko","Tidak perlu"))) -> Pemilik risiko
A27: R-18 | B27: G1 | C27: =INDEX('Risk Register'!$C$6:$C$27,MATCH($A27,'Risk Register'!$A$6:$A$27,0)) -> Karyawan menyerahkan kredensial dan penyerang masuk ke sistem | D27: =INDEX('Risk Register'!$J$6:$J$27,MATCH($A27,'Risk Register'!$A$6:$A$27,0)) -> 16 | E27: =INDEX('Risk Register'!$K$6:$K$27,MATCH($A27,'Risk Register'!$A$6:$A$27,0)) -> Tinggi | F27: =MATCH($A27,Evaluasi!$B$10:$B$31,0) -> 2 | G27: Mitigasi | H27: 6.3, 8.23, 8.7, 8.5, 6.8 | I27: Pelatihan dan simulasi phishing berkala, filter email dan web, MFA tahan phishing untuk sistem kritis, jalur pelaporan email mencurigakan. | J27: Skor 16 tertinggi; phishing tidak bisa dihilangkan, jadi MFA dibuat agar kredensial curian tidak cukup. | K27: =INDEX('Risk Register'!$D$6:$D$27,MATCH($A27,'Risk Register'!$A$6:$A$27,0)) -> Head of IT Support | L27: =IF(G27="Terima",EDATE($D$6,6),$D$6+Evaluasi!$D$6) -> 46397 | M27: 2 | N27: 3 | O27: =M27*N27 -> 6 | P27: =IF(O27<=Kriteria!$B$3,"Rendah",IF(O27<=Kriteria!$B$4,"Sedang",IF(O27<=Kriteria!$B$5,"Tinggi","Kritis"))) -> Sedang | Q27: =IF(O27>Kriteria!$B$6,"Perlu penanganan lanjutan","Dapat diterima") -> Dapat diterima | R27: =IF(E27="Kritis","Direksi",IF(E27="Tinggi","Manajemen",IF(E27="Sedang","Pemilik risiko","Tidak perlu"))) -> Manajemen
A28: R-19 | B28: - | C28: =INDEX('Risk Register'!$C$6:$C$27,MATCH($A28,'Risk Register'!$A$6:$A$27,0)) -> Transaksi tertahan atau disusupi | D28: =INDEX('Risk Register'!$J$6:$J$27,MATCH($A28,'Risk Register'!$A$6:$A$27,0)) -> 8 | E28: =INDEX('Risk Register'!$K$6:$K$27,MATCH($A28,'Risk Register'!$A$6:$A$27,0)) -> Sedang | F28: =MATCH($A28,Evaluasi!$B$10:$B$31,0) -> 20 | G28: Terima | H28: - | I28: Dipantau pada tinjauan berkala 6 bulan. | J28: Skor 8; terkendali lewat SLA dan kontak teknis dengan bank mitra. | K28: =INDEX('Risk Register'!$D$6:$D$27,MATCH($A28,'Risk Register'!$A$6:$A$27,0)) -> Head of Partnership | L28: =IF(G28="Terima",EDATE($D$6,6),$D$6+Evaluasi!$D$6) -> 46489 | M28: =INDEX('Risk Register'!$E$6:$E$27,MATCH($A28,'Risk Register'!$A$6:$A$27,0)) -> 2 | N28: =INDEX('Risk Register'!$I$6:$I$27,MATCH($A28,'Risk Register'!$A$6:$A$27,0)) -> 4 | O28: =M28*N28 -> 8 | P28: =IF(O28<=Kriteria!$B$3,"Rendah",IF(O28<=Kriteria!$B$4,"Sedang",IF(O28<=Kriteria!$B$5,"Tinggi","Kritis"))) -> Sedang | Q28: =IF(O28>Kriteria!$B$6,"Perlu penanganan lanjutan","Dapat diterima") -> Dapat diterima | R28: =IF(E28="Kritis","Direksi",IF(E28="Tinggi","Manajemen",IF(E28="Sedang","Pemilik risiko","Tidak perlu"))) -> Pemilik risiko
A29: R-20 | B29: G6 | C29: =INDEX('Risk Register'!$C$6:$C$27,MATCH($A29,'Risk Register'!$A$6:$A$27,0)) -> Data KYC pengguna bocor dari penyedia | D29: =INDEX('Risk Register'!$J$6:$J$27,MATCH($A29,'Risk Register'!$A$6:$A$27,0)) -> 10 | E29: =INDEX('Risk Register'!$K$6:$K$27,MATCH($A29,'Risk Register'!$A$6:$A$27,0)) -> Tinggi | F29: =MATCH($A29,Evaluasi!$B$10:$B$31,0) -> 12 | G29: Mitigasi dan transfer | H29: 5.19, 5.20, 5.22, 5.34 | I29: Penilaian keamanan vendor sebelum dan berkala, klausul keamanan dan notifikasi insiden di kontrak, batasi retensi data di vendor, ganti rugi kontraktual. | J29: Skor 10 di atas batas; LumiPay tidak mengendalikan sistem vendor, jadi kontrol berupa pengawasan dan kontrak, dengan transfer sebagian risiko lewat kontrak. | K29: =INDEX('Risk Register'!$D$6:$D$27,MATCH($A29,'Risk Register'!$A$6:$A$27,0)) -> Compliance Officer | L29: =IF(G29="Terima",EDATE($D$6,6),$D$6+Evaluasi!$D$6) -> 46397 | M29: 2 | N29: 4 | O29: =M29*N29 -> 8 | P29: =IF(O29<=Kriteria!$B$3,"Rendah",IF(O29<=Kriteria!$B$4,"Sedang",IF(O29<=Kriteria!$B$5,"Tinggi","Kritis"))) -> Sedang | Q29: =IF(O29>Kriteria!$B$6,"Perlu penanganan lanjutan","Dapat diterima") -> Dapat diterima | R29: =IF(E29="Kritis","Direksi",IF(E29="Tinggi","Manajemen",IF(E29="Sedang","Pemilik risiko","Tidak perlu"))) -> Manajemen
A30: R-21 | B30: - | C30: =INDEX('Risk Register'!$C$6:$C$27,MATCH($A30,'Risk Register'!$A$6:$A$27,0)) -> Pengguna tidak bisa login atau bertransaksi, atau OTP disalahgunakan | D30: =INDEX('Risk Register'!$J$6:$J$27,MATCH($A30,'Risk Register'!$A$6:$A$27,0)) -> 9 | E30: =INDEX('Risk Register'!$K$6:$K$27,MATCH($A30,'Risk Register'!$A$6:$A$27,0)) -> Sedang | F30: =MATCH($A30,Evaluasi!$B$10:$B$31,0) -> 17 | G30: Terima | H30: - | I30: Dipantau pada tinjauan berkala 6 bulan. | J30: Skor 9, tepat di batas penerimaan; ditinjau tiap 6 bulan. | K30: =INDEX('Risk Register'!$D$6:$D$27,MATCH($A30,'Risk Register'!$A$6:$A$27,0)) -> Head of Engineering | L30: =IF(G30="Terima",EDATE($D$6,6),$D$6+Evaluasi!$D$6) -> 46489 | M30: =INDEX('Risk Register'!$E$6:$E$27,MATCH($A30,'Risk Register'!$A$6:$A$27,0)) -> 3 | N30: =INDEX('Risk Register'!$I$6:$I$27,MATCH($A30,'Risk Register'!$A$6:$A$27,0)) -> 3 | O30: =M30*N30 -> 9 | P30: =IF(O30<=Kriteria!$B$3,"Rendah",IF(O30<=Kriteria!$B$4,"Sedang",IF(O30<=Kriteria!$B$5,"Tinggi","Kritis"))) -> Sedang | Q30: =IF(O30>Kriteria!$B$6,"Perlu penanganan lanjutan","Dapat diterima") -> Dapat diterima | R30: =IF(E30="Kritis","Direksi",IF(E30="Tinggi","Manajemen",IF(E30="Sedang","Pemilik risiko","Tidak perlu"))) -> Pemilik risiko
A31: R-22 | B31: - | C31: =INDEX('Risk Register'!$C$6:$C$27,MATCH($A31,'Risk Register'!$A$6:$A$27,0)) -> Pengetahuan kritis hilang dan akses mantan karyawan masih aktif | D31: =INDEX('Risk Register'!$J$6:$J$27,MATCH($A31,'Risk Register'!$A$6:$A$27,0)) -> 9 | E31: =INDEX('Risk Register'!$K$6:$K$27,MATCH($A31,'Risk Register'!$A$6:$A$27,0)) -> Sedang | F31: =MATCH($A31,Evaluasi!$B$10:$B$31,0) -> 18 | G31: Terima | H31: - | I31: Dipantau pada tinjauan berkala 6 bulan. | J31: Skor 9, tepat di batas penerimaan; ditinjau tiap 6 bulan. | K31: =INDEX('Risk Register'!$D$6:$D$27,MATCH($A31,'Risk Register'!$A$6:$A$27,0)) -> Head of HR | L31: =IF(G31="Terima",EDATE($D$6,6),$D$6+Evaluasi!$D$6) -> 46489 | M31: =INDEX('Risk Register'!$E$6:$E$27,MATCH($A31,'Risk Register'!$A$6:$A$27,0)) -> 3 | N31: =INDEX('Risk Register'!$I$6:$I$27,MATCH($A31,'Risk Register'!$A$6:$A$27,0)) -> 3 | O31: =M31*N31 -> 9 | P31: =IF(O31<=Kriteria!$B$3,"Rendah",IF(O31<=Kriteria!$B$4,"Sedang",IF(O31<=Kriteria!$B$5,"Tinggi","Kritis"))) -> Sedang | Q31: =IF(O31>Kriteria!$B$6,"Perlu penanganan lanjutan","Dapat diterima") -> Dapat diterima | R31: =IF(E31="Kritis","Direksi",IF(E31="Tinggi","Manajemen",IF(E31="Sedang","Pemilik risiko","Tidak perlu"))) -> Pemilik risiko
A33: Catatan: kontrol diambil dari ISO/IEC 27002:2022 (Annex A 27001:2022). Nilai risiko sisa adalah perkiraan setelah kontrol diterapkan dan perlu diverifikasi.
A34: Opsi 'Hindari' dan 'Transfer penuh' belum dipakai; transfer dipakai sebagian (R-15 dan R-20). Risiko yang diterima wajib punya alasan tertulis dan persetujuan pemilik risiko.

Sheet Kelompok
A1: Kelompok Penanganan Risiko
A2: Risiko yang akar masalahnya sama ditangani bersama, supaya satu perbaikan menutup beberapa risiko sekaligus.
A4: Kode | B4: Kelompok | C4: Akar masalah | D4: Risiko terkait | E4: Tindakan inti | F4: Kontrol Annex A utama | G4: Jumlah risiko
A5: G1 | B5: Akses dan autentikasi | C5: Akun dan hak akses kurang terlindungi (tanpa MFA, hak akses luas, akun lama). | D5: R-02, R-04, R-12, R-18 | E5: MFA wajib, hak akses minimum, tinjauan hak akses berkala, pemisahan tugas, pelatihan phishing. | F5: 5.3, 5.15, 5.18, 8.2, 8.5, 6.3 | G5: =COUNTIF(Penanganan!$B$10:$B$31,A5) -> 4
A6: G2 | B6: Kode dan pipeline | C6: Akses repositori dan pengelolaan secret lemah. | D6: R-05, R-06, R-07 | E6: Secrets manager dan secret scanning, MFA repositori, branch protection dan review wajib, pencabutan akun lama. | F6: 8.4, 8.24, 5.17, 8.32, 5.18, 8.5 | G6: =COUNTIF(Penanganan!$B$10:$B$31,A6) -> 3
A7: G3 | B7: Keamanan aplikasi dan API | C7: Kontrol keamanan saat pengembangan aplikasi dan API belum memadai. | D7: R-01, R-11 | E7: Secure coding, query berparameter, pengujian otorisasi per objek, SAST dan pentest, manajemen patch. | F7: 8.26, 8.28, 8.29, 8.8 | G7: =COUNTIF(Penanganan!$B$10:$B$31,A7) -> 2
A8: G4 | B8: Ketahanan layanan dan data | C8: Ketahanan terhadap serangan ketersediaan dan pemulihan data belum teruji. | D8: R-10, R-15 | E8: Rate limiting dan proteksi DDoS, backup terisolasi yang diuji, rencana pemulihan, asuransi siber. | F8: 8.6, 8.20, 8.21, 8.13, 5.30 | G8: =COUNTIF(Penanganan!$B$10:$B$31,A8) -> 2
A9: G5 | B9: Konfigurasi cloud | C9: Baseline konfigurasi cloud tidak dijaga otomatis. | D9: R-03 | E9: Blok akses publik, enkripsi at-rest, pemindaian konfigurasi dengan alert. | F9: 8.9, 8.3, 8.24, 5.23 | G9: =COUNTIF(Penanganan!$B$10:$B$31,A9) -> 1
A10: G6 | B10: Pihak ketiga | C10: Vendor pemroses data pribadi belum dinilai dan kontraknya belum memuat syarat keamanan. | D10: R-20 | E10: Penilaian vendor, klausul keamanan dan notifikasi insiden, batas retensi data, ganti rugi kontraktual. | F10: 5.19, 5.20, 5.22, 5.34 | G10: =COUNTIF(Penanganan!$B$10:$B$31,A10) -> 1
A11: G7 | B11: Pemantauan dan log | C11: Log tidak memadai, padahal dibutuhkan semua kontrol deteksi. | D11: R-13 | E11: Retensi log, perlindungan integritas log, alerting kejadian kritis. | F11: 8.15, 8.16 | G11: =COUNTIF(Penanganan!$B$10:$B$31,A11) -> 1

Sheet Kriteria
A1: Kriteria Risiko LumiPay (rujukan penilaian)
A2: Sel biru adalah parameter yang boleh diubah. Seluruh sheet lain membaca nilainya dari sini.
A3: Batas atas level Rendah (skor) | B3: 4
A4: Batas atas level Sedang (skor) | B4: 9
A5: Batas atas level Tinggi (skor) | B5: 16
A6: Batas penerimaan risiko (skor) | B6: =B4 -> 9
A7: Skor di atas batas Tinggi (16) masuk level Kritis (20 sampai 25). Batas penerimaan LumiPay sama dengan batas atas level Sedang.
A9: Matriks risiko: kemungkinan x dampak
A10: Kemungkinan \ Dampak | B10: 1 | C10: 2 | D10: 3 | E10: 4 | F10: 5
A11: 5 | B11: =$A11*B$10 -> 5 | C11: =$A11*C$10 -> 10 | D11: =$A11*D$10 -> 15 | E11: =$A11*E$10 -> 20 | F11: =$A11*F$10 -> 25
A12: 4 | B12: =$A12*B$10 -> 4 | C12: =$A12*C$10 -> 8 | D12: =$A12*D$10 -> 12 | E12: =$A12*E$10 -> 16 | F12: =$A12*F$10 -> 20
A13: 3 | B13: =$A13*B$10 -> 3 | C13: =$A13*C$10 -> 6 | D13: =$A13*D$10 -> 9 | E13: =$A13*E$10 -> 12 | F13: =$A13*F$10 -> 15
A14: 2 | B14: =$A14*B$10 -> 2 | C14: =$A14*C$10 -> 4 | D14: =$A14*D$10 -> 6 | E14: =$A14*E$10 -> 8 | F14: =$A14*F$10 -> 10
A15: 1 | B15: =$A15*B$10 -> 1 | C15: =$A15*C$10 -> 2 | D15: =$A15*D$10 -> 3 | E15: =$A15*E$10 -> 4 | F15: =$A15*F$10 -> 5
A17: Warna matriks memakai batas tetap 4, 9, dan 16 (sama dengan parameter di atas). Jika parameter diubah, sesuaikan aturan warnanya.

Sheet Ringkasan
A1: Ringkasan Hasil Analisis
A3: Level | B3: Jumlah risiko
A4: Rendah | B4: =COUNTIF('Risk Register'!$K$6:$K$27,A4) -> 0
A5: Sedang | B5: =COUNTIF('Risk Register'!$K$6:$K$27,A5) -> 10
A6: Tinggi | B6: =COUNTIF('Risk Register'!$K$6:$K$27,A6) -> 12
A7: Kritis | B7: =COUNTIF('Risk Register'!$K$6:$K$27,A7) -> 0
A8: Total risiko | B8: =SUM(B4:B7) -> 22
A9: Perlu ditangani (di atas batas penerimaan) | B9: =COUNTIF('Risk Register'!$L$6:$L$27,"Perlu ditangani") -> 12
A10: Skor tertinggi | B10: =MAX('Risk Register'!$J$6:$J$27) -> 16
A12: Penanganan risiko (langkah 5)
A13: Risiko dimitigasi (termasuk mitigasi dan transfer) | B13: =COUNTIF(Penanganan!$G$10:$G$31,"Mitigasi*") -> 14
A14: Risiko diterima | B14: =COUNTIF(Penanganan!$G$10:$G$31,"Terima") -> 8
A15: Risiko sisa di atas batas penerimaan | B15: =COUNTIF(Penanganan!$Q$10:$Q$31,"Perlu penanganan lanjutan") -> 0
A16: Skor sisa tertinggi | B16: =MAX(Penanganan!$O$10:$O$31) -> 9
A17: Jumlah kelompok penanganan | B17: =COUNTA(Kelompok!$A$5:$A$11) -> 7
A19: Cek Annex A dan SoA (langkah 6)
A20: Total kontrol dinilai | B20: =COUNTA(SoA!$A$7:$A$99) -> 93
A21: Kontrol berlaku | B21: =COUNTIF(SoA!$D$7:$D$99,"Ya") -> 84
A22: Kontrol tidak berlaku | B22: =COUNTIF(SoA!$D$7:$D$99,"Tidak") -> 9
A23: Berlaku karena dipilih dari risiko | B23: =COUNTIFS(SoA!$D$7:$D$99,"Ya",SoA!$E$7:$E$99,"Risiko") -> 34
A24: Berlaku karena hukum, kontrak, ISO, atau praktik dasar | B24: =B21-B23 -> 50
A25: Status Sudah diterapkan | B25: =COUNTIF(SoA!$I$7:$I$99,"Sudah diterapkan") -> 2
A26: Status Sebagian | B26: =COUNTIF(SoA!$I$7:$I$99,"Sebagian") -> 45
A27: Status Terencana | B27: =COUNTIF(SoA!$I$7:$I$99,"Terencana") -> 36
A28: Status Belum | B28: =COUNTIF(SoA!$I$7:$I$99,"Belum") -> 1
A29: Baris pemetaan risiko ke kontrol | B29: =COUNTA(Pemetaan!$A$5:$A$64) -> 60
A30: Kontrol dengan cek konsistensi bermasalah | B30: =COUNTIF(SoA!$M$7:$M$99,"<>OK") -> 0
A31: Bukti tersedia: Ada | B31: =COUNTIF(SoA!$L$7:$L$99,"Ada") -> 2
A32: Bukti tersedia: Sebagian | B32: =COUNTIF(SoA!$L$7:$L$99,"Sebagian") -> 45
A33: Bukti tersedia: Belum ada | B33: =COUNTIF(SoA!$L$7:$L$99,"Belum ada") -> 37
A34: Risiko dimitigasi tanpa satu pun kontrol di pemetaan | B34: =SUMPRODUCT((LEFT(Penanganan!$G$10:$G$31,8)="Mitigasi")*(COUNTIF(Pemetaan!$A$5:$A$64,Penanganan!$A$10:$A$31)=0)) -> 0

Sheet Pemetaan
A1: Pemetaan Risiko ke Kontrol Annex A (langkah 6)
A2: Lembar kerja pendukung SoA. Setiap baris menghubungkan satu risiko dengan satu kontrol Annex A yang dipilih di rencana penanganan (langkah 5), diambil dari kolom Kontrol Annex A 2022 di sheet Penanganan. Satu risiko bisa muncul di beberapa baris, dan satu kontrol juga bisa muncul di beberapa baris (hubungan banyak ke banyak). Risiko berstatus Terima tidak muncul di sini karena tidak punya kontrol tambahan. Sheet SoA memakai tabel ini untuk menghitung jumlah risiko per kontrol. Pengecekan konsistensinya dilakukan di SoA, bukan di sini. Catatan: tabel ini berisi nilai tetap, bukan rumus. Kalau kolom Kontrol di sheet Penanganan diubah, baris di sini harus diperbarui manual.
A4: Risiko | B4: Kontrol | C4: Nama kontrol
A5: R-01 | B5: 8.26 | C5: =INDEX(SoA!$C$7:$C$99,MATCH(B5,SoA!$A$7:$A$99,0)) -> Application security requirements
A6: R-01 | B6: 8.28 | C6: =INDEX(SoA!$C$7:$C$99,MATCH(B6,SoA!$A$7:$A$99,0)) -> Secure coding
A7: R-01 | B7: 8.29 | C7: =INDEX(SoA!$C$7:$C$99,MATCH(B7,SoA!$A$7:$A$99,0)) -> Security testing in development and acceptance
A8: R-01 | B8: 8.8 | C8: =INDEX(SoA!$C$7:$C$99,MATCH(B8,SoA!$A$7:$A$99,0)) -> Management of technical vulnerabilities
A9: R-02 | B9: 5.15 | C9: =INDEX(SoA!$C$7:$C$99,MATCH(B9,SoA!$A$7:$A$99,0)) -> Access control
A10: R-02 | B10: 5.18 | C10: =INDEX(SoA!$C$7:$C$99,MATCH(B10,SoA!$A$7:$A$99,0)) -> Access rights
A11: R-02 | B11: 8.2 | C11: =INDEX(SoA!$C$7:$C$99,MATCH(B11,SoA!$A$7:$A$99,0)) -> Privileged access rights
A12: R-02 | B12: 8.3 | C12: =INDEX(SoA!$C$7:$C$99,MATCH(B12,SoA!$A$7:$A$99,0)) -> Information access restriction
A13: R-02 | B13: 8.5 | C13: =INDEX(SoA!$C$7:$C$99,MATCH(B13,SoA!$A$7:$A$99,0)) -> Secure authentication
A14: R-02 | B14: 8.15 | C14: =INDEX(SoA!$C$7:$C$99,MATCH(B14,SoA!$A$7:$A$99,0)) -> Logging
A15: R-03 | B15: 8.9 | C15: =INDEX(SoA!$C$7:$C$99,MATCH(B15,SoA!$A$7:$A$99,0)) -> Configuration management
A16: R-03 | B16: 8.3 | C16: =INDEX(SoA!$C$7:$C$99,MATCH(B16,SoA!$A$7:$A$99,0)) -> Information access restriction
... A64: R-20 | B64: 5.34 | C64: =INDEX(SoA!$C$7:$C$99,MATCH(B64,SoA!$A$7:$A$99,0)) -> Privacy and protection of PII

Sheet SoA
A1: Statement of Applicability (SoA) LumiPay v1.0 (14 Okt 2026) (langkah 6)
A2: Seluruh 93 kontrol ISO/IEC 27001:2022 Annex A dinilai satu per satu: berlaku atau tidak, dasarnya, alasannya, dan status penerapan. Status dan ketersediaan bukti adalah asumsi dummy untuk portofolio.
A3: Tanggal acuan penanganan | C3: =Penanganan!$D$6 -> 46307
A4: Dasar pemilihan: Risiko = dipilih dari rencana penanganan; Hukum dan kontrak; Persyaratan ISO 27001; Praktik dasar; Tidak berlaku.
A5: Tanggal pemeriksaan SoA | C5: 46309 | E5: Ubah ke tanggal pemeriksaan sebenarnya (atau isi =TODAY()). Aturan cek konsistensi ada di bawah tabel.
A6: No | B6: Tema | C6: Kontrol | D6: Berlaku | E6: Dasar pemilihan | F6: Risiko terkait | G6: Jml risiko | H6: Justifikasi | I6: Status penerapan | J6: Target | K6: Bukti yang diharapkan | L6: Bukti tersedia | M6: Cek konsistensi
A7: 5.1 | B7: Organisasi | C7: Policies for information security | D7: Ya | E7: Persyaratan ISO 27001 | F7: - | G7: =COUNTIF(Pemetaan!$B$5:$B$64,A7) -> 0 | H7: Kebijakan keamanan informasi wajib ada (Klausul 5.2) dan disetujui manajemen. | I7: Sebagian | J7: - | K7: Dokumen kebijakan keamanan informasi dan bukti persetujuan manajemen | L7: Sebagian | M7: =IF(AND(D7="Tidak",G7>0),"Konflik: ada risiko terkait",IF(AND(D7="Ya",E7="Risiko",G7=0),"Tidak ada risiko terkait",IF(AND(D7="Ya",I7="-"),"Status kosong",IF(AND(I7="Sudah diterapkan",L7<>"Ada"),"Status Sudah tanpa bukti lengkap",IF(AND(I7="Sebagian",L7="Belum ada"),"Status Sebagian tanpa bukti",IF(AND(I7="Terencana",L7="Ada"),"Terencana tapi bukti sudah ada, cek statusnya",IF(AND(I7="Terencana",ISNUMBER(J7),J7<$C$5),"Target terlewat","OK"))))))) -> OK
A8: 5.2 | B8: Organisasi | C8: Roles and responsibilities | D8: Ya | E8: Persyaratan ISO 27001 | F8: - | G8: =COUNTIF(Pemetaan!$B$5:$B$64,A8) -> 0 | H8: Peran dan tanggung jawab keamanan informasi harus ditetapkan (Klausul 5.3). | I8: Sebagian | J8: - | K8: Matriks peran dan tanggung jawab, surat penugasan | L8: Sebagian | M8: =IF(AND(D8="Tidak",G8>0),"Konflik: ada risiko terkait",IF(AND(D8="Ya",E8="Risiko",G8=0),"Tidak ada risiko terkait",IF(AND(D8="Ya",I8="-"),"Status kosong",IF(AND(I8="Sudah diterapkan",L8<>"Ada"),"Status Sudah tanpa bukti lengkap",IF(AND(I8="Sebagian",L8="Belum ada"),"Status Sebagian tanpa bukti",IF(AND(I8="Terencana",L8="Ada"),"Terencana tapi bukti sudah ada, cek statusnya",IF(AND(I8="Terencana",ISNUMBER(J8),J8<$C$5),"Target terlewat","OK"))))))) -> OK
A9: 5.3 | B9: Organisasi | C9: Segregation of duties | D9: Ya | E9: Risiko | F9: R-04 | G9: =COUNTIF(Pemetaan!$B$5:$B$64,A9) -> 1 | H9: Pemisahan tugas pengubah dan penyetuju data ledger. | I9: Terencana | J9: =IF(E9="Risiko",$C$3+Evaluasi!$D$6,EDATE($C$3,6)) -> 46397 | K9: Matriks pemisahan tugas, log persetujuan perubahan ledger | L9: Belum ada | M9: =IF(AND(D9="Tidak",G9>0),"Konflik: ada risiko terkait",IF(AND(D9="Ya",E9="Risiko",G9=0),"Tidak ada risiko terkait",IF(AND(D9="Ya",I9="-"),"Status kosong",IF(AND(I9="Sudah diterapkan",L9<>"Ada"),"Status Sudah tanpa bukti lengkap",IF(AND(I9="Sebagian",L9="Belum ada"),"Status Sebagian tanpa bukti",IF(AND(I9="Terencana",L9="Ada"),"Terencana tapi bukti sudah ada, cek statusnya",IF(AND(I9="Terencana",ISNUMBER(J9),J9<$C$5),"Target terlewat","OK"))))))) -> OK
A10: 5.4 | B10: Organisasi | C10: Management responsibilities | D10: Ya | E10: Persyaratan ISO 27001 | F10: - | G10: =COUNTIF(Pemetaan!$B$5:$B$64,A10) -> 0 | H10: Manajemen wajib menunjukkan komitmen dan mewajibkan karyawan menerapkan kebijakan (Klausul 5.1). | I10: Sebagian | J10: - | K10: Notulen tinjauan manajemen, komunikasi kebijakan dari direksi | L10: Sebagian | M10: =IF(AND(D10="Tidak",G10>0),"Konflik: ada risiko terkait",IF(AND(D10="Ya",E10="Risiko",G10=0),"Tidak ada risiko terkait",IF(AND(D10="Ya",I10="-"),"Status kosong",IF(AND(I10="Sudah diterapkan",L10<>"Ada"),"Status Sudah tanpa bukti lengkap",IF(AND(I10="Sebagian",L10="Belum ada"),"Status Sebagian tanpa bukti",IF(AND(I10="Terencana",L10="Ada"),"Terencana tapi bukti sudah ada, cek statusnya",IF(AND(I10="Terencana",ISNUMBER(J10),J10<$C$5),"Target terlewat","OK"))))))) -> OK
A11: 5.5 | B11: Organisasi | C11: Contact with authorities | D11: Ya | E11: Hukum dan kontrak | F11: - | G11: =COUNTIF(Pemetaan!$B$5:$B$64,A11) -> 0 | H11: Insiden pada penyelenggara jasa pembayaran dan data pribadi harus dilaporkan ke otoritas (Bank Indonesia, otoritas PDP) dan bank mitra. | I11: Sebagian | J11: - | K11: Daftar kontak otoritas dan bank mitra, prosedur pelaporan | L11: Sebagian | M11: =IF(AND(D11="Tidak",G11>0),"Konflik: ada risiko terkait",IF(AND(D11="Ya",E11="Risiko",G11=0),"Tidak ada risiko terkait",IF(AND(D11="Ya",I11="-"),"Status kosong",IF(AND(I11="Sudah diterapkan",L11<>"Ada"),"Status Sudah tanpa bukti lengkap",IF(AND(I11="Sebagian",L11="Belum ada"),"Status Sebagian tanpa bukti",IF(AND(I11="Terencana",L11="Ada"),"Terencana tapi bukti sudah ada, cek statusnya",IF(AND(I11="Terencana",ISNUMBER(J11),J11<$C$5),"Target terlewat","OK"))))))) -> OK
A12: 5.6 | B12: Organisasi | C12: Contact with special interest groups | D12: Tidak | E12: Tidak berlaku | F12: - | G12: =COUNTIF(Pemetaan!$B$5:$B$64,A12) -> 0 | H12: Keanggotaan kelompok minat khusus bersifat opsional dan tidak dibutuhkan untuk mengendalikan risiko R-01 sampai R-22. Ancaman terkini dipantau lewat 8.16. | I12: - | J12: - | K12: Justifikasi tertulis pengecualian | L12: - | M12: =IF(AND(D12="Tidak",G12>0),"Konflik: ada risiko terkait",IF(AND(D12="Ya",E12="Risiko",G12=0),"Tidak ada risiko terkait",IF(AND(D12="Ya",I12="-"),"Status kosong",IF(AND(I12="Sudah diterapkan",L12<>"Ada"),"Status Sudah tanpa bukti lengkap",IF(AND(I12="Sebagian",L12="Belum ada"),"Status Sebagian tanpa bukti",IF(AND(I12="Terencana",L12="Ada"),"Terencana tapi bukti sudah ada, cek statusnya",IF(AND(I12="Terencana",ISNUMBER(J12),J12<$C$5),"Target terlewat","OK"))))))) -> OK
A13: 5.7 | B13: Organisasi | C13: Threat intelligence | D13: Tidak | E13: Tidak berlaku | F13: - | G13: =COUNTIF(Pemetaan!$B$5:$B$64,A13) -> 0 | H13: Belum diperlukan pada fase awal ISMS; informasi ancaman dari penyedia cloud dan sumber publik dipakai seperlunya. | I13: - | J13: - | K13: Justifikasi tertulis pengecualian, sumber informasi ancaman yang dipakai | L13: - | M13: =IF(AND(D13="Tidak",G13>0),"Konflik: ada risiko terkait",IF(AND(D13="Ya",E13="Risiko",G13=0),"Tidak ada risiko terkait",IF(AND(D13="Ya",I13="-"),"Status kosong",IF(AND(I13="Sudah diterapkan",L13<>"Ada"),"Status Sudah tanpa bukti lengkap",IF(AND(I13="Sebagian",L13="Belum ada"),"Status Sebagian tanpa bukti",IF(AND(I13="Terencana",L13="Ada"),"Terencana tapi bukti sudah ada, cek statusnya",IF(AND(I13="Terencana",ISNUMBER(J13),J13<$C$5),"Target terlewat","OK"))))))) -> OK
A14: 5.8 | B14: Organisasi | C14: Information security in project management | D14: Ya | E14: Praktik dasar | F14: - | G14: =COUNTIF(Pemetaan!$B$5:$B$64,A14) -> 0 | H14: Isu internal: kontrol sering tertinggal dari rilis fitur. Keamanan perlu masuk ke setiap proyek dan rilis. | I14: Sebagian | J14: - | K14: Checklist keamanan pada proses proyek dan rilis | L14: Sebagian | M14: =IF(AND(D14="Tidak",G14>0),"Konflik: ada risiko terkait",IF(AND(D14="Ya",E14="Risiko",G14=0),"Tidak ada risiko terkait",IF(AND(D14="Ya",I14="-"),"Status kosong",IF(AND(I14="Sudah diterapkan",L14<>"Ada"),"Status Sudah tanpa bukti lengkap",IF(AND(I14="Sebagian",L14="Belum ada"),"Status Sebagian tanpa bukti",IF(AND(I14="Terencana",L14="Ada"),"Terencana tapi bukti sudah ada, cek statusnya",IF(AND(I14="Terencana",ISNUMBER(J14),J14<$C$5),"Target terlewat","OK"))))))) -> OK
A15: 5.9 | B15: Organisasi | C15: Inventory of information and other associated assets | D15: Ya | E15: Persyaratan ISO 27001 | F15: - | G15: =COUNTIF(Pemetaan!$B$5:$B$64,A15) -> 0 | H15: Inventaris aset A-01 sampai A-17 sudah dibuat dan menjadi dasar penilaian risiko. | I15: Sudah diterapkan | J15: - | K15: Dokumen Asset Inventory A-01 sampai A-17 | L15: Ada | M15: =IF(AND(D15="Tidak",G15>0),"Konflik: ada risiko terkait",IF(AND(D15="Ya",E15="Risiko",G15=0),"Tidak ada risiko terkait",IF(AND(D15="Ya",I15="-"),"Status kosong",IF(AND(I15="Sudah diterapkan",L15<>"Ada"),"Status Sudah tanpa bukti lengkap",IF(AND(I15="Sebagian",L15="Belum ada"),"Status Sebagian tanpa bukti",IF(AND(I15="Terencana",L15="Ada"),"Terencana tapi bukti sudah ada, cek statusnya",IF(AND(I15="Terencana",ISNUMBER(J15),J15<$C$5),"Target terlewat","OK"))))))) -> OK
A16: 5.10 | B16: Organisasi | C16: Acceptable use of information and other associated assets | D16: Ya | E16: Praktik dasar | F16: - | G16: =COUNTIF(Pemetaan!$B$5:$B$64,A16) -> 0 | H16: Aturan penggunaan aset yang dapat diterima untuk karyawan dan perangkat kerja. | I16: Sebagian | J16: - | K16: Kebijakan penggunaan aset yang dapat diterima, tanda terima karyawan | L16: Sebagian | M16: =IF(AND(D16="Tidak",G16>0),"Konflik: ada risiko terkait",IF(AND(D16="Ya",E16="Risiko",G16=0),"Tidak ada risiko terkait",IF(AND(D16="Ya",I16="-"),"Status kosong",IF(AND(I16="Sudah diterapkan",L16<>"Ada"),"Status Sudah tanpa bukti lengkap",IF(AND(I16="Sebagian",L16="Belum ada"),"Status Sebagian tanpa bukti",IF(AND(I16="Terencana",L16="Ada"),"Terencana tapi bukti sudah ada, cek statusnya",IF(AND(I16="Terencana",ISNUMBER(J16),J16<$C$5),"Target terlewat","OK"))))))) -> OK
A17: 5.11 | B17: Organisasi | C17: Return of assets | D17: Ya | E17: Praktik dasar | F17: - | G17: =COUNTIF(Pemetaan!$B$5:$B$64,A17) -> 0 | H17: Aset dan akses dikembalikan atau dicabut saat karyawan keluar. | I17: Sebagian | J17: - | K17: Formulir serah terima aset, checklist offboarding | L17: Sebagian | M17: =IF(AND(D17="Tidak",G17>0),"Konflik: ada risiko terkait",IF(AND(D17="Ya",E17="Risiko",G17=0),"Tidak ada risiko terkait",IF(AND(D17="Ya",I17="-"),"Status kosong",IF(AND(I17="Sudah diterapkan",L17<>"Ada"),"Status Sudah tanpa bukti lengkap",IF(AND(I17="Sebagian",L17="Belum ada"),"Status Sebagian tanpa bukti",IF(AND(I17="Terencana",L17="Ada"),"Terencana tapi bukti sudah ada, cek statusnya",IF(AND(I17="Terencana",ISNUMBER(J17),J17<$C$5),"Target terlewat","OK"))))))) -> OK
A18: 5.12 | B18: Organisasi | C18: Classification of information | D18: Ya | E18: Hukum dan kontrak | F18: - | G18: =COUNTIF(Pemetaan!$B$5:$B$64,A18) -> 0 | H18: Data pribadi (KTP, swafoto) dan data transaksi perlu diklasifikasi sesuai UU PDP. | I18: Sebagian | J18: - | K18: Skema klasifikasi data, daftar klasifikasi aset | L18: Sebagian | M18: =IF(AND(D18="Tidak",G18>0),"Konflik: ada risiko terkait",IF(AND(D18="Ya",E18="Risiko",G18=0),"Tidak ada risiko terkait",IF(AND(D18="Ya",I18="-"),"Status kosong",IF(AND(I18="Sudah diterapkan",L18<>"Ada"),"Status Sudah tanpa bukti lengkap",IF(AND(I18="Sebagian",L18="Belum ada"),"Status Sebagian tanpa bukti",IF(AND(I18="Terencana",L18="Ada"),"Terencana tapi bukti sudah ada, cek statusnya",IF(AND(I18="Terencana",ISNUMBER(J18),J18<$C$5),"Target terlewat","OK"))))))) -> OK
A19: 5.13 | B19: Organisasi | C19: Labelling of information | D19: Tidak | E19: Tidak berlaku | F19: - | G19: =COUNTIF(Pemetaan!$B$5:$B$64,A19) -> 0 | H19: Mayoritas informasi berbentuk digital dan dilindungi lewat klasifikasi (5.12) serta kontrol akses; pelabelan dokumen tidak dibutuhkan. | I19: - | J19: - | K19: Justifikasi tertulis pengecualian, skema klasifikasi (5.12) | L19: - | M19: =IF(AND(D19="Tidak",G19>0),"Konflik: ada risiko terkait",IF(AND(D19="Ya",E19="Risiko",G19=0),"Tidak ada risiko terkait",IF(AND(D19="Ya",I19="-"),"Status kosong",IF(AND(I19="Sudah diterapkan",L19<>"Ada"),"Status Sudah tanpa bukti lengkap",IF(AND(I19="Sebagian",L19="Belum ada"),"Status Sebagian tanpa bukti",IF(AND(I19="Terencana",L19="Ada"),"Terencana tapi bukti sudah ada, cek statusnya",IF(AND(I19="Terencana",ISNUMBER(J19),J19<$C$5),"Target terlewat","OK"))))))) -> OK
A20: 5.14 | B20: Organisasi | C20: Information transfer | D20: Ya | E20: Hukum dan kontrak | F20: - | G20: =COUNTIF(Pemetaan!$B$5:$B$64,A20) -> 0 | H20: Pertukaran data transaksi dengan bank mitra, jaringan QRIS, dan vendor lewat API. | I20: Sebagian | J20: - | K20: Perjanjian pertukaran data dengan bank mitra, konfigurasi enkripsi API | L20: Sebagian | M20: =IF(AND(D20="Tidak",G20>0),"Konflik: ada risiko terkait",IF(AND(D20="Ya",E20="Risiko",G20=0),"Tidak ada risiko terkait",IF(AND(D20="Ya",I20="-"),"Status kosong",IF(AND(I20="Sudah diterapkan",L20<>"Ada"),"Status Sudah tanpa bukti lengkap",IF(AND(I20="Sebagian",L20="Belum ada"),"Status Sebagian tanpa bukti",IF(AND(I20="Terencana",L20="Ada"),"Terencana tapi bukti sudah ada, cek statusnya",IF(AND(I20="Terencana",ISNUMBER(J20),J20<$C$5),"Target terlewat","OK"))))))) -> OK
A21: 5.15 | B21: Organisasi | C21: Access control | D21: Ya | E21: Risiko | F21: R-02 | G21: =COUNTIF(Pemetaan!$B$5:$B$64,A21) -> 1 | H21: Akses ke data KYC berbasis peran. | I21: Terencana | J21: =IF(E21="Risiko",$C$3+Evaluasi!$D$6,EDATE($C$3,6)) -> 46397 | K21: Kebijakan kontrol akses, matriks peran akses | L21: Belum ada | M21: =IF(AND(D21="Tidak",G21>0),"Konflik: ada risiko terkait",IF(AND(D21="Ya",E21="Risiko",G21=0),"Tidak ada risiko terkait",IF(AND(D21="Ya",I21="-"),"Status kosong",IF(AND(I21="Sudah diterapkan",L21<>"Ada"),"Status Sudah tanpa bukti lengkap",IF(AND(I21="Sebagian",L21="Belum ada"),"Status Sebagian tanpa bukti",IF(AND(I21="Terencana",L21="Ada"),"Terencana tapi bukti sudah ada, cek statusnya",IF(AND(I21="Terencana",ISNUMBER(J21),J21<$C$5),"Target terlewat","OK"))))))) -> OK
A22: 5.16 | B22: Organisasi | C22: Identity management | D22: Ya | E22: Praktik dasar | F22: - | G22: =COUNTIF(Pemetaan!$B$5:$B$64,A22) -> 0 | H22: Siklus hidup identitas pengguna internal, termasuk pencabutan akun mantan karyawan. | I22: Sebagian | J22: - | K22: Prosedur pembuatan dan penonaktifan akun, daftar akun aktif | L22: Sebagian | M22: =IF(AND(D22="Tidak",G22>0),"Konflik: ada risiko terkait",IF(AND(D22="Ya",E22="Risiko",G22=0),"Tidak ada risiko terkait",IF(AND(D22="Ya",I22="-"),"Status kosong",IF(AND(I22="Sudah diterapkan",L22<>"Ada"),"Status Sudah tanpa bukti lengkap",IF(AND(I22="Sebagian",L22="Belum ada"),"Status Sebagian tanpa bukti",IF(AND(I22="Terencana",L22="Ada"),"Terencana tapi bukti sudah ada, cek statusnya",IF(AND(I22="Terencana",ISNUMBER(J22),J22<$C$5),"Target terlewat","OK"))))))) -> OK
A23: 5.17 | B23: Organisasi | C23: Authentication information | D23: Ya | E23: Risiko | F23: R-05, R-12 | G23: =COUNTIF(Pemetaan!$B$5:$B$64,A23) -> 2 | H23: Pengelolaan kredensial: secret dan kata sandi. | I23: Terencana | J23: =IF(E23="Risiko",$C$3+Evaluasi!$D$6,EDATE($C$3,6)) -> 46397 | K23: Kebijakan kata sandi dan kredensial, konfigurasi secrets manager | L23: Belum ada | M23: =IF(AND(D23="Tidak",G23>0),"Konflik: ada risiko terkait",IF(AND(D23="Ya",E23="Risiko",G23=0),"Tidak ada risiko terkait",IF(AND(D23="Ya",I23="-"),"Status kosong",IF(AND(I23="Sudah diterapkan",L23<>"Ada"),"Status Sudah tanpa bukti lengkap",IF(AND(I23="Sebagian",L23="Belum ada"),"Status Sebagian tanpa bukti",IF(AND(I23="Terencana",L23="Ada"),"Terencana tapi bukti sudah ada, cek statusnya",IF(AND(I23="Terencana",ISNUMBER(J23),J23<$C$5),"Target terlewat","OK"))))))) -> OK
A24: 5.18 | B24: Organisasi | C24: Access rights | D24: Ya | E24: Risiko | F24: R-02, R-06, R-07 | G24: =COUNTIF(Pemetaan!$B$5:$B$64,A24) -> 3 | H24: Hak akses data KYC dan repositori ditinjau dan dicabut. | I24: Terencana | J24: =IF(E24="Risiko",$C$3+Evaluasi!$D$6,EDATE($C$3,6)) -> 46397 | K24: Laporan tinjauan hak akses berkala, tiket pencabutan akses | L24: Belum ada | M24: =IF(AND(D24="Tidak",G24>0),"Konflik: ada risiko terkait",IF(AND(D24="Ya",E24="Risiko",G24=0),"Tidak ada risiko terkait",IF(AND(D24="Ya",I24="-"),"Status kosong",IF(AND(I24="Sudah diterapkan",L24<>"Ada"),"Status Sudah tanpa bukti lengkap",IF(AND(I24="Sebagian",L24="Belum ada"),"Status Sebagian tanpa bukti",IF(AND(I24="Terencana",L24="Ada"),"Terencana tapi bukti sudah ada, cek statusnya",IF(AND(I24="Terencana",ISNUMBER(J24),J24<$C$5),"Target terlewat","OK"))))))) -> OK
A25: 5.19 | B25: Organisasi | C25: Information security in supplier relationships | D25: Ya | E25: Risiko | F25: R-20 | G25: =COUNTIF(Pemetaan!$B$5:$B$64,A25) -> 1 | H25: Pengawasan keamanan vendor KYC. | I25: Terencana | J25: =IF(E25="Risiko",$C$3+Evaluasi!$D$6,EDATE($C$3,6)) -> 46397 | K25: Hasil penilaian keamanan vendor, daftar vendor | L25: Belum ada | M25: =IF(AND(D25="Tidak",G25>0),"Konflik: ada risiko terkait",IF(AND(D25="Ya",E25="Risiko",G25=0),"Tidak ada risiko terkait",IF(AND(D25="Ya",I25="-"),"Status kosong",IF(AND(I25="Sudah diterapkan",L25<>"Ada"),"Status Sudah tanpa bukti lengkap",IF(AND(I25="Sebagian",L25="Belum ada"),"Status Sebagian tanpa bukti",IF(AND(I25="Terencana",L25="Ada"),"Terencana tapi bukti sudah ada, cek statusnya",IF(AND(I25="Terencana",ISNUMBER(J25),J25<$C$5),"Target terlewat","OK"))))))) -> OK
A26: 5.20 | B26: Organisasi | C26: Addressing information security within supplier agreements | D26: Ya | E26: Risiko | F26: R-20 | G26: =COUNTIF(Pemetaan!$B$5:$B$64,A26) -> 1 | H26: Klausul keamanan dan notifikasi insiden di kontrak vendor. | I26: Terencana | J26: =IF(E26="Risiko",$C$3+Evaluasi!$D$6,EDATE($C$3,6)) -> 46397 | K26: Kontrak vendor dengan klausul keamanan dan notifikasi insiden | L26: Belum ada | M26: =IF(AND(D26="Tidak",G26>0),"Konflik: ada risiko terkait",IF(AND(D26="Ya",E26="Risiko",G26=0),"Tidak ada risiko terkait",IF(AND(D26="Ya",I26="-"),"Status kosong",IF(AND(I26="Sudah diterapkan",L26<>"Ada"),"Status Sudah tanpa bukti lengkap",IF(AND(I26="Sebagian",L26="Belum ada"),"Status Sebagian tanpa bukti",IF(AND(I26="Terencana",L26="Ada"),"Terencana tapi bukti sudah ada, cek statusnya",IF(AND(I26="Terencana",ISNUMBER(J26),J26<$C$5),"Target terlewat","OK"))))))) -> OK
A27: 5.21 | B27: Organisasi | C27: Managing information security in the ICT supply chain | D27: Ya | E27: Praktik dasar | F27: - | G27: =COUNTIF(Pemetaan!$B$5:$B$64,A27) -> 0 | H27: Rantai pasok TIK: layanan cloud dan pustaka perangkat lunak pihak ketiga. | I27: Sebagian | J27: - | K27: Daftar dependensi pihak ketiga, hasil pemindaian komponen | L27: Sebagian | M27: =IF(AND(D27="Tidak",G27>0),"Konflik: ada risiko terkait",IF(AND(D27="Ya",E27="Risiko",G27=0),"Tidak ada risiko terkait",IF(AND(D27="Ya",I27="-"),"Status kosong",IF(AND(I27="Sudah diterapkan",L27<>"Ada"),"Status Sudah tanpa bukti lengkap",IF(AND(I27="Sebagian",L27="Belum ada"),"Status Sebagian tanpa bukti",IF(AND(I27="Terencana",L27="Ada"),"Terencana tapi bukti sudah ada, cek statusnya",IF(AND(I27="Terencana",ISNUMBER(J27),J27<$C$5),"Target terlewat","OK"))))))) -> OK
A28: 5.22 | B28: Organisasi | C28: Monitoring, review and change management of supplier services | D28: Ya | E28: Risiko | F28: R-20 | G28: =COUNTIF(Pemetaan!$B$5:$B$64,A28) -> 1 | H28: Pemantauan berkala layanan vendor. | I28: Terencana | J28: =IF(E28="Risiko",$C$3+Evaluasi!$D$6,EDATE($C$3,6)) -> 46397 | K28: Laporan tinjauan layanan vendor berkala | L28: Belum ada | M28: =IF(AND(D28="Tidak",G28>0),"Konflik: ada risiko terkait",IF(AND(D28="Ya",E28="Risiko",G28=0),"Tidak ada risiko terkait",IF(AND(D28="Ya",I28="-"),"Status kosong",IF(AND(I28="Sudah diterapkan",L28<>"Ada"),"Status Sudah tanpa bukti lengkap",IF(AND(I28="Sebagian",L28="Belum ada"),"Status Sebagian tanpa bukti",IF(AND(I28="Terencana",L28="Ada"),"Terencana tapi bukti sudah ada, cek statusnya",IF(AND(I28="Terencana",ISNUMBER(J28),J28<$C$5),"Target terlewat","OK"))))))) -> OK
A29: 5.23 | B29: Organisasi | C29: Information security for use of cloud services | D29: Ya | E29: Risiko | F29: R-03 | G29: =COUNTIF(Pemetaan!$B$5:$B$64,A29) -> 1 | H29: Konfigurasi dan penggunaan layanan cloud yang aman. | I29: Terencana | J29: =IF(E29="Risiko",$C$3+Evaluasi!$D$6,EDATE($C$3,6)) -> 46397 | K29: Kebijakan penggunaan cloud, laporan baseline konfigurasi cloud | L29: Belum ada | M29: =IF(AND(D29="Tidak",G29>0),"Konflik: ada risiko terkait",IF(AND(D29="Ya",E29="Risiko",G29=0),"Tidak ada risiko terkait",IF(AND(D29="Ya",I29="-"),"Status kosong",IF(AND(I29="Sudah diterapkan",L29<>"Ada"),"Status Sudah tanpa bukti lengkap",IF(AND(I29="Sebagian",L29="Belum ada"),"Status Sebagian tanpa bukti",IF(AND(I29="Terencana",L29="Ada"),"Terencana tapi bukti sudah ada, cek statusnya",IF(AND(I29="Terencana",ISNUMBER(J29),J29<$C$5),"Target terlewat","OK"))))))) -> OK
A30: 5.24 | B30: Organisasi | C30: Information security incident management planning and preparation | D30: Ya | E30: Hukum dan kontrak | F30: - | G30: =COUNTIF(Pemetaan!$B$5:$B$64,A30) -> 0 | H30: Bank mitra mensyaratkan laporan insiden tepat waktu; perlu rencana dan peran penanganan insiden. | I30: Sebagian | J30: - | K30: Rencana dan prosedur penanganan insiden, daftar peran | L30: Sebagian | M30: =IF(AND(D30="Tidak",G30>0),"Konflik: ada risiko terkait",IF(AND(D30="Ya",E30="Risiko",G30=0),"Tidak ada risiko terkait",IF(AND(D30="Ya",I30="-"),"Status kosong",IF(AND(I30="Sudah diterapkan",L30<>"Ada"),"Status Sudah tanpa bukti lengkap",IF(AND(I30="Sebagian",L30="Belum ada"),"Status Sebagian tanpa bukti",IF(AND(I30="Terencana",L30="Ada"),"Terencana tapi bukti sudah ada, cek statusnya",IF(AND(I30="Terencana",ISNUMBER(J30),J30<$C$5),"Target terlewat","OK"))))))) -> OK
A31: 5.25 | B31: Organisasi | C31: Assessment and decision on information security events | D31: Ya | E31: Hukum dan kontrak | F31: - | G31: =COUNTIF(Pemetaan!$B$5:$B$64,A31) -> 0 | H31: Kejadian keamanan harus dinilai untuk menentukan apakah menjadi insiden yang wajib dilaporkan. | I31: Sebagian | J31: - | K31: Kriteria klasifikasi insiden, catatan penilaian kejadian | L31: Sebagian | M31: =IF(AND(D31="Tidak",G31>0),"Konflik: ada risiko terkait",IF(AND(D31="Ya",E31="Risiko",G31=0),"Tidak ada risiko terkait",IF(AND(D31="Ya",I31="-"),"Status kosong",IF(AND(I31="Sudah diterapkan",L31<>"Ada"),"Status Sudah tanpa bukti lengkap",IF(AND(I31="Sebagian",L31="Belum ada"),"Status Sebagian tanpa bukti",IF(AND(I31="Terencana",L31="Ada"),"Terencana tapi bukti sudah ada, cek statusnya",IF(AND(I31="Terencana",ISNUMBER(J31),J31<$C$5),"Target terlewat","OK"))))))) -> OK
A32: 5.26 | B32: Organisasi | C32: Response to information security incidents | D32: Ya | E32: Hukum dan kontrak | F32: - | G32: =COUNTIF(Pemetaan!$B$5:$B$64,A32) -> 0 | H32: Respons insiden mengikuti prosedur dan kewajiban pelaporan ke bank mitra dan otoritas. | I32: Sebagian | J32: - | K32: Catatan respons insiden, laporan ke bank mitra dan otoritas | L32: Sebagian | M32: =IF(AND(D32="Tidak",G32>0),"Konflik: ada risiko terkait",IF(AND(D32="Ya",E32="Risiko",G32=0),"Tidak ada risiko terkait",IF(AND(D32="Ya",I32="-"),"Status kosong",IF(AND(I32="Sudah diterapkan",L32<>"Ada"),"Status Sudah tanpa bukti lengkap",IF(AND(I32="Sebagian",L32="Belum ada"),"Status Sebagian tanpa bukti",IF(AND(I32="Terencana",L32="Ada"),"Terencana tapi bukti sudah ada, cek statusnya",IF(AND(I32="Terencana",ISNUMBER(J32),J32<$C$5),"Target terlewat","OK"))))))) -> OK
A33: 5.27 | B33: Organisasi | C33: Learning from information security incidents | D33: Ya | E33: Praktik dasar | F33: - | G33: =COUNTIF(Pemetaan!$B$5:$B$64,A33) -> 0 | H33: Pelajaran dari insiden dipakai memperbarui risiko dan kontrol. | I33: Sebagian | J33: - | K33: Laporan pasca-insiden dan tindak lanjut | L33: Sebagian | M33: =IF(AND(D33="Tidak",G33>0),"Konflik: ada risiko terkait",IF(AND(D33="Ya",E33="Risiko",G33=0),"Tidak ada risiko terkait",IF(AND(D33="Ya",I33="-"),"Status kosong",IF(AND(I33="Sudah diterapkan",L33<>"Ada"),"Status Sudah tanpa bukti lengkap",IF(AND(I33="Sebagian",L33="Belum ada"),"Status Sebagian tanpa bukti",IF(AND(I33="Terencana",L33="Ada"),"Terencana tapi bukti sudah ada, cek statusnya",IF(AND(I33="Terencana",ISNUMBER(J33),J33<$C$5),"Target terlewat","OK"))))))) -> OK
A34: 5.28 | B34: Organisasi | C34: Collection of evidence | D34: Ya | E34: Praktik dasar | F34: - | G34: =COUNTIF(Pemetaan!$B$5:$B$64,A34) -> 0 | H34: Pengumpulan bukti untuk investigasi dan pelaporan ke pihak berwenang. | I34: Sebagian | J34: - | K34: Prosedur pengumpulan bukti digital, catatan rantai bukti | L34: Sebagian | M34: =IF(AND(D34="Tidak",G34>0),"Konflik: ada risiko terkait",IF(AND(D34="Ya",E34="Risiko",G34=0),"Tidak ada risiko terkait",IF(AND(D34="Ya",I34="-"),"Status kosong",IF(AND(I34="Sudah diterapkan",L34<>"Ada"),"Status Sudah tanpa bukti lengkap",IF(AND(I34="Sebagian",L34="Belum ada"),"Status Sebagian tanpa bukti",IF(AND(I34="Terencana",L34="Ada"),"Terencana tapi bukti sudah ada, cek statusnya",IF(AND(I34="Terencana",ISNUMBER(J34),J34<$C$5),"Target terlewat","OK"))))))) -> OK
A35: 5.29 | B35: Organisasi | C35: Information security during disruption | D35: Ya | E35: Risiko | F35: R-15 | G35: =COUNTIF(Pemetaan!$B$5:$B$64,A35) -> 1 | H35: Keamanan informasi saat gangguan (ransomware). | I35: Terencana | J35: =IF(E35="Risiko",$C$3+Evaluasi!$D$6,EDATE($C$3,6)) -> 46397 | K35: Rencana pemulihan, hasil uji pemulihan | L35: Belum ada | M35: =IF(AND(D35="Tidak",G35>0),"Konflik: ada risiko terkait",IF(AND(D35="Ya",E35="Risiko",G35=0),"Tidak ada risiko terkait",IF(AND(D35="Ya",I35="-"),"Status kosong",IF(AND(I35="Sudah diterapkan",L35<>"Ada"),"Status Sudah tanpa bukti lengkap",IF(AND(I35="Sebagian",L35="Belum ada"),"Status Sebagian tanpa bukti",IF(AND(I35="Terencana",L35="Ada"),"Terencana tapi bukti sudah ada, cek statusnya",IF(AND(I35="Terencana",ISNUMBER(J35),J35<$C$5),"Target terlewat","OK"))))))) -> OK
A36: 5.30 | B36: Organisasi | C36: ICT readiness for business continuity | D36: Ya | E36: Risiko | F36: R-15 | G36: =COUNTIF(Pemetaan!$B$5:$B$64,A36) -> 1 | H36: Kesiapan TIK untuk kelangsungan layanan. | I36: Terencana | J36: =IF(E36="Risiko",$C$3+Evaluasi!$D$6,EDATE($C$3,6)) -> 46397 | K36: Rencana kelangsungan layanan, hasil uji failover dan target waktu pemulihan | L36: Belum ada | M36: =IF(AND(D36="Tidak",G36>0),"Konflik: ada risiko terkait",IF(AND(D36="Ya",E36="Risiko",G36=0),"Tidak ada risiko terkait",IF(AND(D36="Ya",I36="-"),"Status kosong",IF(AND(I36="Sudah diterapkan",L36<>"Ada"),"Status Sudah tanpa bukti lengkap",IF(AND(I36="Sebagian",L36="Belum ada"),"Status Sebagian tanpa bukti",IF(AND(I36="Terencana",L36="Ada"),"Terencana tapi bukti sudah ada, cek statusnya",IF(AND(I36="Terencana",ISNUMBER(J36),J36<$C$5),"Target terlewat","OK"))))))) -> OK
A37: 5.31 | B37: Organisasi | C37: Legal, statutory, regulatory and contractual requirements | D37: Ya | E37: Hukum dan kontrak | F37: - | G37: =COUNTIF(Pemetaan!$B$5:$B$64,A37) -> 0 | H37: Kewajiban hukum: UU PDP, ketentuan Bank Indonesia, perjanjian dengan bank mitra. | I37: Belum | J37: - | K37: Daftar persyaratan hukum dan kontrak (legal register), laporan kepatuhan | L37: Belum ada | M37: =IF(AND(D37="Tidak",G37>0),"Konflik: ada risiko terkait",IF(AND(D37="Ya",E37="Risiko",G37=0),"Tidak ada risiko terkait",IF(AND(D37="Ya",I37="-"),"Status kosong",IF(AND(I37="Sudah diterapkan",L37<>"Ada"),"Status Sudah tanpa bukti lengkap",IF(AND(I37="Sebagian",L37="Belum ada"),"Status Sebagian tanpa bukti",IF(AND(I37="Terencana",L37="Ada"),"Terencana tapi bukti sudah ada, cek statusnya",IF(AND(I37="Terencana",ISNUMBER(J37),J37<$C$5),"Target terlewat","OK"))))))) -> OK
A38: 5.32 | B38: Organisasi | C38: Intellectual property rights | D38: Ya | E38: Praktik dasar | F38: - | G38: =COUNTIF(Pemetaan!$B$5:$B$64,A38) -> 0 | H38: Lisensi perangkat lunak dan pustaka sumber terbuka yang dipakai tim engineering. | I38: Sebagian | J38: - | K38: Daftar lisensi perangkat lunak dan pustaka sumber terbuka | L38: Sebagian | M38: =IF(AND(D38="Tidak",G38>0),"Konflik: ada risiko terkait",IF(AND(D38="Ya",E38="Risiko",G38=0),"Tidak ada risiko terkait",IF(AND(D38="Ya",I38="-"),"Status kosong",IF(AND(I38="Sudah diterapkan",L38<>"Ada"),"Status Sudah tanpa bukti lengkap",IF(AND(I38="Sebagian",L38="Belum ada"),"Status Sebagian tanpa bukti",IF(AND(I38="Terencana",L38="Ada"),"Terencana tapi bukti sudah ada, cek statusnya",IF(AND(I38="Terencana",ISNUMBER(J38),J38<$C$5),"Target terlewat","OK"))))))) -> OK
A39: 5.33 | B39: Organisasi | C39: Protection of records | D39: Ya | E39: Hukum dan kontrak | F39: - | G39: =COUNTIF(Pemetaan!$B$5:$B$64,A39) -> 0 | H39: Catatan transaksi dan log harus dijaga dan disimpan sesuai kewajiban retensi. | I39: Sebagian | J39: - | K39: Jadwal retensi catatan, bukti penyimpanan log dan catatan transaksi | L39: Sebagian | M39: =IF(AND(D39="Tidak",G39>0),"Konflik: ada risiko terkait",IF(AND(D39="Ya",E39="Risiko",G39=0),"Tidak ada risiko terkait",IF(AND(D39="Ya",I39="-"),"Status kosong",IF(AND(I39="Sudah diterapkan",L39<>"Ada"),"Status Sudah tanpa bukti lengkap",IF(AND(I39="Sebagian",L39="Belum ada"),"Status Sebagian tanpa bukti",IF(AND(I39="Terencana",L39="Ada"),"Terencana tapi bukti sudah ada, cek statusnya",IF(AND(I39="Terencana",ISNUMBER(J39),J39<$C$5),"Target terlewat","OK"))))))) -> OK
A40: 5.34 | B40: Organisasi | C40: Privacy and protection of PII | D40: Ya | E40: Risiko | F40: R-20 | G40: =COUNTIF(Pemetaan!$B$5:$B$64,A40) -> 1 | H40: Pelindungan data pribadi KYC di vendor, termasuk batas retensi. | I40: Terencana | J40: =IF(E40="Risiko",$C$3+Evaluasi!$D$6,EDATE($C$3,6)) -> 46397 | K40: Kebijakan pelindungan data pribadi, catatan pemrosesan data, perjanjian pemrosesan data dengan vendor | L40: Belum ada | M40: =IF(AND(D40="Tidak",G40>0),"Konflik: ada risiko terkait",IF(AND(D40="Ya",E40="Risiko",G40=0),"Tidak ada risiko terkait",IF(AND(D40="Ya",I40="-"),"Status kosong",IF(AND(I40="Sudah diterapkan",L40<>"Ada"),"Status Sudah tanpa bukti lengkap",IF(AND(I40="Sebagian",L40="Belum ada"),"Status Sebagian tanpa bukti",IF(AND(I40="Terencana",L40="Ada"),"Terencana tapi bukti sudah ada, cek statusnya",IF(AND(I40="Terencana",ISNUMBER(J40),J40<$C$5),"Target terlewat","OK"))))))) -> OK
A41: 5.35 | B41: Organisasi | C41: Independent review of information security | D41: Ya | E41: Persyaratan ISO 27001 | F41: - | G41: =COUNTIF(Pemetaan!$B$5:$B$64,A41) -> 0 | H41: Tinjauan independen lewat audit internal ISMS (Klausul 9.2). | I41: Terencana | J41: =IF(E41="Risiko",$C$3+Evaluasi!$D$6,EDATE($C$3,6)) -> 46489 | K41: Program dan laporan audit internal ISMS | L41: Belum ada | M41: =IF(AND(D41="Tidak",G41>0),"Konflik: ada risiko terkait",IF(AND(D41="Ya",E41="Risiko",G41=0),"Tidak ada risiko terkait",IF(AND(D41="Ya",I41="-"),"Status kosong",IF(AND(I41="Sudah diterapkan",L41<>"Ada"),"Status Sudah tanpa bukti lengkap",IF(AND(I41="Sebagian",L41="Belum ada"),"Status Sebagian tanpa bukti",IF(AND(I41="Terencana",L41="Ada"),"Terencana tapi bukti sudah ada, cek statusnya",IF(AND(I41="Terencana",ISNUMBER(J41),J41<$C$5),"Target terlewat","OK"))))))) -> OK
A42: 5.36 | B42: Organisasi | C42: Compliance with policies, rules and standards for information security | D42: Ya | E42: Persyaratan ISO 27001 | F42: - | G42: =COUNTIF(Pemetaan!$B$5:$B$64,A42) -> 0 | H42: Kepatuhan terhadap kebijakan dilaporkan dalam tinjauan manajemen (Klausul 9.3). | I42: Sebagian | J42: - | K42: Laporan kepatuhan kebijakan, bahan tinjauan manajemen | L42: Sebagian | M42: =IF(AND(D42="Tidak",G42>0),"Konflik: ada risiko terkait",IF(AND(D42="Ya",E42="Risiko",G42=0),"Tidak ada risiko terkait",IF(AND(D42="Ya",I42="-"),"Status kosong",IF(AND(I42="Sudah diterapkan",L42<>"Ada"),"Status Sudah tanpa bukti lengkap",IF(AND(I42="Sebagian",L42="Belum ada"),"Status Sebagian tanpa bukti",IF(AND(I42="Terencana",L42="Ada"),"Terencana tapi bukti sudah ada, cek statusnya",IF(AND(I42="Terencana",ISNUMBER(J42),J42<$C$5),"Target terlewat","OK"))))))) -> OK
A43: 5.37 | B43: Organisasi | C43: Documented operating procedures | D43: Ya | E43: Praktik dasar | F43: - | G43: =COUNTIF(Pemetaan!$B$5:$B$64,A43) -> 0 | H43: Prosedur operasi (rilis, akses produksi, backup) harus terdokumentasi. | I43: Sebagian | J43: - | K43: Prosedur operasi terdokumentasi (rilis, akses produksi, backup) | L43: Sebagian | M43: =IF(AND(D43="Tidak",G43>0),"Konflik: ada risiko terkait",IF(AND(D43="Ya",E43="Risiko",G43=0),"Tidak ada risiko terkait",IF(AND(D43="Ya",I43="-"),"Status kosong",IF(AND(I43="Sudah diterapkan",L43<>"Ada"),"Status Sudah tanpa bukti lengkap",IF(AND(I43="Sebagian",L43="Belum ada"),"Status Sebagian tanpa bukti",IF(AND(I43="Terencana",L43="Ada"),"Terencana tapi bukti sudah ada, cek statusnya",IF(AND(I43="Terencana",ISNUMBER(J43),J43<$C$5),"Target terlewat","OK"))))))) -> OK
A44: 6.1 | B44: Manusia | C44: Screening | D44: Ya | E44: Praktik dasar | F44: - | G44: =COUNTIF(Pemetaan!$B$5:$B$64,A44) -> 0 | H44: Verifikasi latar belakang karyawan yang mengakses data KYC dan lingkungan produksi. | I44: Sebagian | J44: - | K44: Kebijakan screening, hasil pemeriksaan latar belakang | L44: Sebagian | M44: =IF(AND(D44="Tidak",G44>0),"Konflik: ada risiko terkait",IF(AND(D44="Ya",E44="Risiko",G44=0),"Tidak ada risiko terkait",IF(AND(D44="Ya",I44="-"),"Status kosong",IF(AND(I44="Sudah diterapkan",L44<>"Ada"),"Status Sudah tanpa bukti lengkap",IF(AND(I44="Sebagian",L44="Belum ada"),"Status Sebagian tanpa bukti",IF(AND(I44="Terencana",L44="Ada"),"Terencana tapi bukti sudah ada, cek statusnya",IF(AND(I44="Terencana",ISNUMBER(J44),J44<$C$5),"Target terlewat","OK"))))))) -> OK
A45: 6.2 | B45: Manusia | C45: Terms and conditions of employment | D45: Ya | E45: Praktik dasar | F45: - | G45: =COUNTIF(Pemetaan!$B$5:$B$64,A45) -> 0 | H45: Kontrak kerja memuat tanggung jawab keamanan informasi. | I45: Sebagian | J45: - | K45: Kontrak kerja dengan klausul keamanan informasi | L45: Sebagian | M45: =IF(AND(D45="Tidak",G45>0),"Konflik: ada risiko terkait",IF(AND(D45="Ya",E45="Risiko",G45=0),"Tidak ada risiko terkait",IF(AND(D45="Ya",I45="-"),"Status kosong",IF(AND(I45="Sudah diterapkan",L45<>"Ada"),"Status Sudah tanpa bukti lengkap",IF(AND(I45="Sebagian",L45="Belum ada"),"Status Sebagian tanpa bukti",IF(AND(I45="Terencana",L45="Ada"),"Terencana tapi bukti sudah ada, cek statusnya",IF(AND(I45="Terencana",ISNUMBER(J45),J45<$C$5),"Target terlewat","OK"))))))) -> OK
A46: 6.3 | B46: Manusia | C46: Information security awareness, education and training | D46: Ya | E46: Risiko | F46: R-18 | G46: =COUNTIF(Pemetaan!$B$5:$B$64,A46) -> 1 | H46: Pelatihan dan simulasi phishing. | I46: Terencana | J46: =IF(E46="Risiko",$C$3+Evaluasi!$D$6,EDATE($C$3,6)) -> 46397 | K46: Materi dan daftar hadir pelatihan, hasil simulasi phishing | L46: Belum ada | M46: =IF(AND(D46="Tidak",G46>0),"Konflik: ada risiko terkait",IF(AND(D46="Ya",E46="Risiko",G46=0),"Tidak ada risiko terkait",IF(AND(D46="Ya",I46="-"),"Status kosong",IF(AND(I46="Sudah diterapkan",L46<>"Ada"),"Status Sudah tanpa bukti lengkap",IF(AND(I46="Sebagian",L46="Belum ada"),"Status Sebagian tanpa bukti",IF(AND(I46="Terencana",L46="Ada"),"Terencana tapi bukti sudah ada, cek statusnya",IF(AND(I46="Terencana",ISNUMBER(J46),J46<$C$5),"Target terlewat","OK"))))))) -> OK
A47: 6.4 | B47: Manusia | C47: Disciplinary process | D47: Ya | E47: Praktik dasar | F47: - | G47: =COUNTIF(Pemetaan!$B$5:$B$64,A47) -> 0 | H47: Proses disipliner untuk pelanggaran kebijakan keamanan. | I47: Sebagian | J47: - | K47: Kebijakan sanksi disiplin | L47: Sebagian | M47: =IF(AND(D47="Tidak",G47>0),"Konflik: ada risiko terkait",IF(AND(D47="Ya",E47="Risiko",G47=0),"Tidak ada risiko terkait",IF(AND(D47="Ya",I47="-"),"Status kosong",IF(AND(I47="Sudah diterapkan",L47<>"Ada"),"Status Sudah tanpa bukti lengkap",IF(AND(I47="Sebagian",L47="Belum ada"),"Status Sebagian tanpa bukti",IF(AND(I47="Terencana",L47="Ada"),"Terencana tapi bukti sudah ada, cek statusnya",IF(AND(I47="Terencana",ISNUMBER(J47),J47<$C$5),"Target terlewat","OK"))))))) -> OK
A48: 6.5 | B48: Manusia | C48: Responsibilities after termination or change of employment | D48: Ya | E48: Praktik dasar | F48: - | G48: =COUNTIF(Pemetaan!$B$5:$B$64,A48) -> 0 | H48: Tanggung jawab dan pencabutan akses setelah karyawan keluar atau berpindah peran. | I48: Sebagian | J48: - | K48: Checklist offboarding, bukti pencabutan akses | L48: Sebagian | M48: =IF(AND(D48="Tidak",G48>0),"Konflik: ada risiko terkait",IF(AND(D48="Ya",E48="Risiko",G48=0),"Tidak ada risiko terkait",IF(AND(D48="Ya",I48="-"),"Status kosong",IF(AND(I48="Sudah diterapkan",L48<>"Ada"),"Status Sudah tanpa bukti lengkap",IF(AND(I48="Sebagian",L48="Belum ada"),"Status Sebagian tanpa bukti",IF(AND(I48="Terencana",L48="Ada"),"Terencana tapi bukti sudah ada, cek statusnya",IF(AND(I48="Terencana",ISNUMBER(J48),J48<$C$5),"Target terlewat","OK"))))))) -> OK
A49: 6.6 | B49: Manusia | C49: Confidentiality or non-disclosure agreements | D49: Ya | E49: Hukum dan kontrak | F49: - | G49: =COUNTIF(Pemetaan!$B$5:$B$64,A49) -> 0 | H49: Perjanjian kerahasiaan untuk karyawan dan pihak ketiga yang menyentuh data pengguna. | I49: Sebagian | J49: - | K49: Perjanjian kerahasiaan yang ditandatangani | L49: Sebagian | M49: =IF(AND(D49="Tidak",G49>0),"Konflik: ada risiko terkait",IF(AND(D49="Ya",E49="Risiko",G49=0),"Tidak ada risiko terkait",IF(AND(D49="Ya",I49="-"),"Status kosong",IF(AND(I49="Sudah diterapkan",L49<>"Ada"),"Status Sudah tanpa bukti lengkap",IF(AND(I49="Sebagian",L49="Belum ada"),"Status Sebagian tanpa bukti",IF(AND(I49="Terencana",L49="Ada"),"Terencana tapi bukti sudah ada, cek statusnya",IF(AND(I49="Terencana",ISNUMBER(J49),J49<$C$5),"Target terlewat","OK"))))))) -> OK
A50: 6.7 | B50: Manusia | C50: Remote working | D50: Ya | E50: Praktik dasar | F50: - | G50: =COUNTIF(Pemetaan!$B$5:$B$64,A50) -> 0 | H50: Karyawan, terutama engineering, bekerja dengan perangkat portabel di luar kantor. | I50: Sebagian | J50: - | K50: Kebijakan kerja jarak jauh, konfigurasi VPN dan perangkat | L50: Sebagian | M50: =IF(AND(D50="Tidak",G50>0),"Konflik: ada risiko terkait",IF(AND(D50="Ya",E50="Risiko",G50=0),"Tidak ada risiko terkait",IF(AND(D50="Ya",I50="-"),"Status kosong",IF(AND(I50="Sudah diterapkan",L50<>"Ada"),"Status Sudah tanpa bukti lengkap",IF(AND(I50="Sebagian",L50="Belum ada"),"Status Sebagian tanpa bukti",IF(AND(I50="Terencana",L50="Ada"),"Terencana tapi bukti sudah ada, cek statusnya",IF(AND(I50="Terencana",ISNUMBER(J50),J50<$C$5),"Target terlewat","OK"))))))) -> OK
A51: 6.8 | B51: Manusia | C51: Information security event reporting | D51: Ya | E51: Risiko | F51: R-18 | G51: =COUNTIF(Pemetaan!$B$5:$B$64,A51) -> 1 | H51: Jalur pelaporan email mencurigakan. | I51: Terencana | J51: =IF(E51="Risiko",$C$3+Evaluasi!$D$6,EDATE($C$3,6)) -> 46397 | K51: Prosedur dan saluran pelaporan, catatan laporan masuk | L51: Belum ada | M51: =IF(AND(D51="Tidak",G51>0),"Konflik: ada risiko terkait",IF(AND(D51="Ya",E51="Risiko",G51=0),"Tidak ada risiko terkait",IF(AND(D51="Ya",I51="-"),"Status kosong",IF(AND(I51="Sudah diterapkan",L51<>"Ada"),"Status Sudah tanpa bukti lengkap",IF(AND(I51="Sebagian",L51="Belum ada"),"Status Sebagian tanpa bukti",IF(AND(I51="Terencana",L51="Ada"),"Terencana tapi bukti sudah ada, cek statusnya",IF(AND(I51="Terencana",ISNUMBER(J51),J51<$C$5),"Target terlewat","OK"))))))) -> OK
A52: 7.1 | B52: Fisik | C52: Physical security perimeters | D52: Ya | E52: Praktik dasar | F52: - | G52: =COUNTIF(Pemetaan!$B$5:$B$64,A52) -> 0 | H52: Batas fisik kantor pusat Surabaya. | I52: Sebagian | J52: - | K52: Denah dan pengamanan perimeter kantor Surabaya | L52: Sebagian | M52: =IF(AND(D52="Tidak",G52>0),"Konflik: ada risiko terkait",IF(AND(D52="Ya",E52="Risiko",G52=0),"Tidak ada risiko terkait",IF(AND(D52="Ya",I52="-"),"Status kosong",IF(AND(I52="Sudah diterapkan",L52<>"Ada"),"Status Sudah tanpa bukti lengkap",IF(AND(I52="Sebagian",L52="Belum ada"),"Status Sebagian tanpa bukti",IF(AND(I52="Terencana",L52="Ada"),"Terencana tapi bukti sudah ada, cek statusnya",IF(AND(I52="Terencana",ISNUMBER(J52),J52<$C$5),"Target terlewat","OK"))))))) -> OK
A53: 7.2 | B53: Fisik | C53: Physical entry | D53: Ya | E53: Praktik dasar | F53: - | G53: =COUNTIF(Pemetaan!$B$5:$B$64,A53) -> 0 | H53: Kontrol masuk ke kantor pusat. | I53: Sebagian | J53: - | K53: Log akses masuk, daftar kartu akses | L53: Sebagian | M53: =IF(AND(D53="Tidak",G53>0),"Konflik: ada risiko terkait",IF(AND(D53="Ya",E53="Risiko",G53=0),"Tidak ada risiko terkait",IF(AND(D53="Ya",I53="-"),"Status kosong",IF(AND(I53="Sudah diterapkan",L53<>"Ada"),"Status Sudah tanpa bukti lengkap",IF(AND(I53="Sebagian",L53="Belum ada"),"Status Sebagian tanpa bukti",IF(AND(I53="Terencana",L53="Ada"),"Terencana tapi bukti sudah ada, cek statusnya",IF(AND(I53="Terencana",ISNUMBER(J53),J53<$C$5),"Target terlewat","OK"))))))) -> OK
A54: 7.3 | B54: Fisik | C54: Securing offices, rooms and facilities | D54: Ya | E54: Praktik dasar | F54: - | G54: =COUNTIF(Pemetaan!$B$5:$B$64,A54) -> 0 | H54: Pengamanan ruang kerja dan ruang perangkat di kantor pusat. | I54: Sebagian | J54: - | K54: Bukti pengamanan ruang kerja dan ruang perangkat | L54: Sebagian | M54: =IF(AND(D54="Tidak",G54>0),"Konflik: ada risiko terkait",IF(AND(D54="Ya",E54="Risiko",G54=0),"Tidak ada risiko terkait",IF(AND(D54="Ya",I54="-"),"Status kosong",IF(AND(I54="Sudah diterapkan",L54<>"Ada"),"Status Sudah tanpa bukti lengkap",IF(AND(I54="Sebagian",L54="Belum ada"),"Status Sebagian tanpa bukti",IF(AND(I54="Terencana",L54="Ada"),"Terencana tapi bukti sudah ada, cek statusnya",IF(AND(I54="Terencana",ISNUMBER(J54),J54<$C$5),"Target terlewat","OK"))))))) -> OK
A55: 7.4 | B55: Fisik | C55: Physical security monitoring | D55: Ya | E55: Praktik dasar | F55: - | G55: =COUNTIF(Pemetaan!$B$5:$B$64,A55) -> 0 | H55: Pemantauan fisik kantor (CCTV dan akses). | I55: Sebagian | J55: - | K55: Rekaman CCTV, log pemantauan | L55: Sebagian | M55: =IF(AND(D55="Tidak",G55>0),"Konflik: ada risiko terkait",IF(AND(D55="Ya",E55="Risiko",G55=0),"Tidak ada risiko terkait",IF(AND(D55="Ya",I55="-"),"Status kosong",IF(AND(I55="Sudah diterapkan",L55<>"Ada"),"Status Sudah tanpa bukti lengkap",IF(AND(I55="Sebagian",L55="Belum ada"),"Status Sebagian tanpa bukti",IF(AND(I55="Terencana",L55="Ada"),"Terencana tapi bukti sudah ada, cek statusnya",IF(AND(I55="Terencana",ISNUMBER(J55),J55<$C$5),"Target terlewat","OK"))))))) -> OK
A56: 7.5 | B56: Fisik | C56: Protecting against physical and environmental threats | D56: Ya | E56: Praktik dasar | F56: - | G56: =COUNTIF(Pemetaan!$B$5:$B$64,A56) -> 0 | H56: Perlindungan kantor dari kebakaran dan ancaman lingkungan. | I56: Sebagian | J56: - | K56: Bukti alat pemadam dan proteksi kebakaran | L56: Sebagian | M56: =IF(AND(D56="Tidak",G56>0),"Konflik: ada risiko terkait",IF(AND(D56="Ya",E56="Risiko",G56=0),"Tidak ada risiko terkait",IF(AND(D56="Ya",I56="-"),"Status kosong",IF(AND(I56="Sudah diterapkan",L56<>"Ada"),"Status Sudah tanpa bukti lengkap",IF(AND(I56="Sebagian",L56="Belum ada"),"Status Sebagian tanpa bukti",IF(AND(I56="Terencana",L56="Ada"),"Terencana tapi bukti sudah ada, cek statusnya",IF(AND(I56="Terencana",ISNUMBER(J56),J56<$C$5),"Target terlewat","OK"))))))) -> OK
A57: 7.6 | B57: Fisik | C57: Working in secure areas | D57: Tidak | E57: Tidak berlaku | F57: - | G57: =COUNTIF(Pemetaan!$B$5:$B$64,A57) -> 0 | H57: Tidak ada area aman khusus di kantor; sistem produksi berada di cloud dan keamanan fisiknya ditangani penyedia cloud. | I57: - | J57: - | K57: Justifikasi tertulis pengecualian, diagram arsitektur sistem produksi | L57: - | M57: =IF(AND(D57="Tidak",G57>0),"Konflik: ada risiko terkait",IF(AND(D57="Ya",E57="Risiko",G57=0),"Tidak ada risiko terkait",IF(AND(D57="Ya",I57="-"),"Status kosong",IF(AND(I57="Sudah diterapkan",L57<>"Ada"),"Status Sudah tanpa bukti lengkap",IF(AND(I57="Sebagian",L57="Belum ada"),"Status Sebagian tanpa bukti",IF(AND(I57="Terencana",L57="Ada"),"Terencana tapi bukti sudah ada, cek statusnya",IF(AND(I57="Terencana",ISNUMBER(J57),J57<$C$5),"Target terlewat","OK"))))))) -> OK
A58: 7.7 | B58: Fisik | C58: Clear desk and clear screen | D58: Ya | E58: Praktik dasar | F58: - | G58: =COUNTIF(Pemetaan!$B$5:$B$64,A58) -> 0 | H58: Meja dan layar bersih agar dokumen dan sesi kerja tidak terlihat orang lain. | I58: Sebagian | J58: - | K58: Kebijakan clear desk dan clear screen, hasil inspeksi | L58: Sebagian | M58: =IF(AND(D58="Tidak",G58>0),"Konflik: ada risiko terkait",IF(AND(D58="Ya",E58="Risiko",G58=0),"Tidak ada risiko terkait",IF(AND(D58="Ya",I58="-"),"Status kosong",IF(AND(I58="Sudah diterapkan",L58<>"Ada"),"Status Sudah tanpa bukti lengkap",IF(AND(I58="Sebagian",L58="Belum ada"),"Status Sebagian tanpa bukti",IF(AND(I58="Terencana",L58="Ada"),"Terencana tapi bukti sudah ada, cek statusnya",IF(AND(I58="Terencana",ISNUMBER(J58),J58<$C$5),"Target terlewat","OK"))))))) -> OK
A59: 7.8 | B59: Fisik | C59: Equipment siting and protection | D59: Ya | E59: Praktik dasar | F59: - | G59: =COUNTIF(Pemetaan!$B$5:$B$64,A59) -> 0 | H59: Penempatan dan perlindungan perangkat kantor. | I59: Sebagian | J59: - | K59: Bukti penempatan dan perlindungan perangkat kantor | L59: Sebagian | M59: =IF(AND(D59="Tidak",G59>0),"Konflik: ada risiko terkait",IF(AND(D59="Ya",E59="Risiko",G59=0),"Tidak ada risiko terkait",IF(AND(D59="Ya",I59="-"),"Status kosong",IF(AND(I59="Sudah diterapkan",L59<>"Ada"),"Status Sudah tanpa bukti lengkap",IF(AND(I59="Sebagian",L59="Belum ada"),"Status Sebagian tanpa bukti",IF(AND(I59="Terencana",L59="Ada"),"Terencana tapi bukti sudah ada, cek statusnya",IF(AND(I59="Terencana",ISNUMBER(J59),J59<$C$5),"Target terlewat","OK"))))))) -> OK
A60: 7.9 | B60: Fisik | C60: Security of assets off-premises | D60: Tidak | E60: Tidak berlaku | F60: - | G60: =COUNTIF(Pemetaan!$B$5:$B$64,A60) -> 0 | H60: Seluruh sistem produksi berada di cloud sehingga tidak ada aset sensitif di luar lokasi. | I60: - | J60: - | K60: Justifikasi tertulis pengecualian, diagram arsitektur sistem | L60: - | M60: =IF(AND(D60="Tidak",G60>0),"Konflik: ada risiko terkait",IF(AND(D60="Ya",E60="Risiko",G60=0),"Tidak ada risiko terkait",IF(AND(D60="Ya",I60="-"),"Status kosong",IF(AND(I60="Sudah diterapkan",L60<>"Ada"),"Status Sudah tanpa bukti lengkap",IF(AND(I60="Sebagian",L60="Belum ada"),"Status Sebagian tanpa bukti",IF(AND(I60="Terencana",L60="Ada"),"Terencana tapi bukti sudah ada, cek statusnya",IF(AND(I60="Terencana",ISNUMBER(J60),J60<$C$5),"Target terlewat","OK"))))))) -> OK
A61: 7.10 | B61: Fisik | C61: Storage media | D61: Ya | E61: Praktik dasar | F61: - | G61: =COUNTIF(Pemetaan!$B$5:$B$64,A61) -> 0 | H61: Media penyimpanan yang dibawa atau dipakai karyawan. | I61: Sebagian | J61: - | K61: Prosedur penggunaan media penyimpanan | L61: Sebagian | M61: =IF(AND(D61="Tidak",G61>0),"Konflik: ada risiko terkait",IF(AND(D61="Ya",E61="Risiko",G61=0),"Tidak ada risiko terkait",IF(AND(D61="Ya",I61="-"),"Status kosong",IF(AND(I61="Sudah diterapkan",L61<>"Ada"),"Status Sudah tanpa bukti lengkap",IF(AND(I61="Sebagian",L61="Belum ada"),"Status Sebagian tanpa bukti",IF(AND(I61="Terencana",L61="Ada"),"Terencana tapi bukti sudah ada, cek statusnya",IF(AND(I61="Terencana",ISNUMBER(J61),J61<$C$5),"Target terlewat","OK"))))))) -> OK
A62: 7.11 | B62: Fisik | C62: Supporting utilities | D62: Tidak | E62: Tidak berlaku | F62: - | G62: =COUNTIF(Pemetaan!$B$5:$B$64,A62) -> 0 | H62: Utilitas pendukung server produksi (listrik, pendingin) dikelola penyedia cloud. | I62: - | J62: - | K62: Justifikasi tertulis pengecualian, laporan kepatuhan penyedia cloud | L62: - | M62: =IF(AND(D62="Tidak",G62>0),"Konflik: ada risiko terkait",IF(AND(D62="Ya",E62="Risiko",G62=0),"Tidak ada risiko terkait",IF(AND(D62="Ya",I62="-"),"Status kosong",IF(AND(I62="Sudah diterapkan",L62<>"Ada"),"Status Sudah tanpa bukti lengkap",IF(AND(I62="Sebagian",L62="Belum ada"),"Status Sebagian tanpa bukti",IF(AND(I62="Terencana",L62="Ada"),"Terencana tapi bukti sudah ada, cek statusnya",IF(AND(I62="Terencana",ISNUMBER(J62),J62<$C$5),"Target terlewat","OK"))))))) -> OK
A63: 7.12 | B63: Fisik | C63: Cabling security | D63: Tidak | E63: Tidak berlaku | F63: - | G63: =COUNTIF(Pemetaan!$B$5:$B$64,A63) -> 0 | H63: Kabel jaringan data center produksi dikelola penyedia cloud; kantor tidak menjalankan sistem produksi. | I63: - | J63: - | K63: Justifikasi tertulis pengecualian, laporan kepatuhan penyedia cloud | L63: - | M63: =IF(AND(D63="Tidak",G63>0),"Konflik: ada risiko terkait",IF(AND(D63="Ya",E63="Risiko",G63=0),"Tidak ada risiko terkait",IF(AND(D63="Ya",I63="-"),"Status kosong",IF(AND(I63="Sudah diterapkan",L63<>"Ada"),"Status Sudah tanpa bukti lengkap",IF(AND(I63="Sebagian",L63="Belum ada"),"Status Sebagian tanpa bukti",IF(AND(I63="Terencana",L63="Ada"),"Terencana tapi bukti sudah ada, cek statusnya",IF(AND(I63="Terencana",ISNUMBER(J63),J63<$C$5),"Target terlewat","OK"))))))) -> OK
... A66: 8.1 | B66: Teknologi | C66: User endpoint devices | D66: Ya | E66: Praktik dasar | F66: - | G66: =COUNTIF(Pemetaan!$B$5:$B$64,A66) -> 0 | H66: Laptop karyawan menyimpan data kerja. Enkripsi disk belum dijalankan (lihat R-17 yang diterima). | I66: Sebagian | J66: - | K66: Daftar perangkat, konfigurasi MDM dan enkripsi disk | L66: Sebagian | M66: =IF(AND(D66="Tidak",G66>0),"Konflik: ada risiko terkait",IF(AND(D66="Ya",E66="Risiko",G66=0),"Tidak ada risiko terkait",IF(AND(D66="Ya",I66="-"),"Status kosong",IF(AND(I66="Sudah diterapkan",L66<>"Ada"),"Status Sudah tanpa bukti lengkap",IF(AND(I66="Sebagian",L66="Belum ada"),"Status Sebagian tanpa bukti",IF(AND(I66="Terencana",L66="Ada"),"Terencana tapi bukti sudah ada, cek statusnya",IF(AND(I66="Terencana",ISNUMBER(J66),J66<$C$5),"Target terlewat","OK"))))))) -> OK
A67: 8.2 | B67: Teknologi | C67: Privileged access rights | D67: Ya | E67: Risiko | F67: R-02, R-04 | G67: =COUNTIF(Pemetaan!$B$5:$B$64,A67) -> 2 | H67: Hak akses istimewa dibatasi. | I67: Terencana | J67: =IF(E67="Risiko",$C$3+Evaluasi!$D$6,EDATE($C$3,6)) -> 46397 | K67: Daftar akun berhak istimewa, log penggunaan | L67: Belum ada | M67: =IF(AND(D67="Tidak",G67>0),"Konflik: ada risiko terkait",IF(AND(D67="Ya",E67="Risiko",G67=0),"Tidak ada risiko terkait",IF(AND(D67="Ya",I67="-"),"Status kosong",IF(AND(I67="Sudah diterapkan",L67<>"Ada"),"Status Sudah tanpa bukti lengkap",IF(AND(I67="Sebagian",L67="Belum ada"),"Status Sebagian tanpa bukti",IF(AND(I67="Terencana",L67="Ada"),"Terencana tapi bukti sudah ada, cek statusnya",IF(AND(I67="Terencana",ISNUMBER(J67),J67<$C$5),"Target terlewat","OK"))))))) -> OK
A68: 8.3 | B68: Teknologi | C68: Information access restriction | D68: Ya | E68: Risiko | F68: R-02, R-03, R-04, R-06, R-11 | G68: =COUNTIF(Pemetaan!$B$5:$B$64,A68) -> 5 | H68: Pembatasan akses informasi (data KYC, storage, repositori, API). | I68: Terencana | J68: =IF(E68="Risiko",$C$3+Evaluasi!$D$6,EDATE($C$3,6)) -> 46397 | K68: Matriks hak akses, konfigurasi akses storage dan database | L68: Belum ada | M68: =IF(AND(D68="Tidak",G68>0),"Konflik: ada risiko terkait",IF(AND(D68="Ya",E68="Risiko",G68=0),"Tidak ada risiko terkait",IF(AND(D68="Ya",I68="-"),"Status kosong",IF(AND(I68="Sudah diterapkan",L68<>"Ada"),"Status Sudah tanpa bukti lengkap",IF(AND(I68="Sebagian",L68="Belum ada"),"Status Sebagian tanpa bukti",IF(AND(I68="Terencana",L68="Ada"),"Terencana tapi bukti sudah ada, cek statusnya",IF(AND(I68="Terencana",ISNUMBER(J68),J68<$C$5),"Target terlewat","OK"))))))) -> OK
A69: 8.4 | B69: Teknologi | C69: Access to source code | D69: Ya | E69: Risiko | F69: R-05, R-06, R-07 | G69: =COUNTIF(Pemetaan!$B$5:$B$64,A69) -> 3 | H69: Akses kode sumber dan repositori. | I69: Terencana | J69: =IF(E69="Risiko",$C$3+Evaluasi!$D$6,EDATE($C$3,6)) -> 46397 | K69: Konfigurasi akses repositori, daftar anggota dan peran | L69: Belum ada | M69: =IF(AND(D69="Tidak",G69>0),"Konflik: ada risiko terkait",IF(AND(D69="Ya",E69="Risiko",G69=0),"Tidak ada risiko terkait",IF(AND(D69="Ya",I69="-"),"Status kosong",IF(AND(I69="Sudah diterapkan",L69<>"Ada"),"Status Sudah tanpa bukti lengkap",IF(AND(I69="Sebagian",L69="Belum ada"),"Status Sebagian tanpa bukti",IF(AND(I69="Terencana",L69="Ada"),"Terencana tapi bukti sudah ada, cek statusnya",IF(AND(I69="Terencana",ISNUMBER(J69),J69<$C$5),"Target terlewat","OK"))))))) -> OK
A70: 8.5 | B70: Teknologi | C70: Secure authentication | D70: Ya | E70: Risiko | F70: R-02, R-06, R-07, R-12, R-18 | G70: =COUNTIF(Pemetaan!$B$5:$B$64,A70) -> 5 | H70: MFA dan autentikasi aman. | I70: Terencana | J70: =IF(E70="Risiko",$C$3+Evaluasi!$D$6,EDATE($C$3,6)) -> 46397 | K70: Konfigurasi MFA, laporan cakupan MFA | L70: Belum ada | M70: =IF(AND(D70="Tidak",G70>0),"Konflik: ada risiko terkait",IF(AND(D70="Ya",E70="Risiko",G70=0),"Tidak ada risiko terkait",IF(AND(D70="Ya",I70="-"),"Status kosong",IF(AND(I70="Sudah diterapkan",L70<>"Ada"),"Status Sudah tanpa bukti lengkap",IF(AND(I70="Sebagian",L70="Belum ada"),"Status Sebagian tanpa bukti",IF(AND(I70="Terencana",L70="Ada"),"Terencana tapi bukti sudah ada, cek statusnya",IF(AND(I70="Terencana",ISNUMBER(J70),J70<$C$5),"Target terlewat","OK"))))))) -> OK
A71: 8.6 | B71: Teknologi | C71: Capacity management | D71: Ya | E71: Risiko | F71: R-10 | G71: =COUNTIF(Pemetaan!$B$5:$B$64,A71) -> 1 | H71: Kapasitas dan lonjakan trafik (DDoS). | I71: Terencana | J71: =IF(E71="Risiko",$C$3+Evaluasi!$D$6,EDATE($C$3,6)) -> 46397 | K71: Laporan kapasitas, hasil uji beban | L71: Belum ada | M71: =IF(AND(D71="Tidak",G71>0),"Konflik: ada risiko terkait",IF(AND(D71="Ya",E71="Risiko",G71=0),"Tidak ada risiko terkait",IF(AND(D71="Ya",I71="-"),"Status kosong",IF(AND(I71="Sudah diterapkan",L71<>"Ada"),"Status Sudah tanpa bukti lengkap",IF(AND(I71="Sebagian",L71="Belum ada"),"Status Sebagian tanpa bukti",IF(AND(I71="Terencana",L71="Ada"),"Terencana tapi bukti sudah ada, cek statusnya",IF(AND(I71="Terencana",ISNUMBER(J71),J71<$C$5),"Target terlewat","OK"))))))) -> OK
A72: 8.7 | B72: Teknologi | C72: Protection against malware | D72: Ya | E72: Risiko | F72: R-15, R-18 | G72: =COUNTIF(Pemetaan!$B$5:$B$64,A72) -> 2 | H72: Proteksi malware dan ransomware. | I72: Terencana | J72: =IF(E72="Risiko",$C$3+Evaluasi!$D$6,EDATE($C$3,6)) -> 46397 | K72: Bukti agen proteksi endpoint, laporan deteksi | L72: Belum ada | M72: =IF(AND(D72="Tidak",G72>0),"Konflik: ada risiko terkait",IF(AND(D72="Ya",E72="Risiko",G72=0),"Tidak ada risiko terkait",IF(AND(D72="Ya",I72="-"),"Status kosong",IF(AND(I72="Sudah diterapkan",L72<>"Ada"),"Status Sudah tanpa bukti lengkap",IF(AND(I72="Sebagian",L72="Belum ada"),"Status Sebagian tanpa bukti",IF(AND(I72="Terencana",L72="Ada"),"Terencana tapi bukti sudah ada, cek statusnya",IF(AND(I72="Terencana",ISNUMBER(J72),J72<$C$5),"Target terlewat","OK"))))))) -> OK
A73: 8.8 | B73: Teknologi | C73: Management of technical vulnerabilities | D73: Ya | E73: Risiko | F73: R-01 | G73: =COUNTIF(Pemetaan!$B$5:$B$64,A73) -> 1 | H73: Patch kerentanan teknis. | I73: Terencana | J73: =IF(E73="Risiko",$C$3+Evaluasi!$D$6,EDATE($C$3,6)) -> 46397 | K73: Laporan pemindaian kerentanan, catatan patching | L73: Belum ada | M73: =IF(AND(D73="Tidak",G73>0),"Konflik: ada risiko terkait",IF(AND(D73="Ya",E73="Risiko",G73=0),"Tidak ada risiko terkait",IF(AND(D73="Ya",I73="-"),"Status kosong",IF(AND(I73="Sudah diterapkan",L73<>"Ada"),"Status Sudah tanpa bukti lengkap",IF(AND(I73="Sebagian",L73="Belum ada"),"Status Sebagian tanpa bukti",IF(AND(I73="Terencana",L73="Ada"),"Terencana tapi bukti sudah ada, cek statusnya",IF(AND(I73="Terencana",ISNUMBER(J73),J73<$C$5),"Target terlewat","OK"))))))) -> OK
A74: 8.9 | B74: Teknologi | C74: Configuration management | D74: Ya | E74: Risiko | F74: R-03 | G74: =COUNTIF(Pemetaan!$B$5:$B$64,A74) -> 1 | H74: Baseline konfigurasi cloud. | I74: Terencana | J74: =IF(E74="Risiko",$C$3+Evaluasi!$D$6,EDATE($C$3,6)) -> 46397 | K74: Baseline konfigurasi, hasil pemindaian konfigurasi | L74: Belum ada | M74: =IF(AND(D74="Tidak",G74>0),"Konflik: ada risiko terkait",IF(AND(D74="Ya",E74="Risiko",G74=0),"Tidak ada risiko terkait",IF(AND(D74="Ya",I74="-"),"Status kosong",IF(AND(I74="Sudah diterapkan",L74<>"Ada"),"Status Sudah tanpa bukti lengkap",IF(AND(I74="Sebagian",L74="Belum ada"),"Status Sebagian tanpa bukti",IF(AND(I74="Terencana",L74="Ada"),"Terencana tapi bukti sudah ada, cek statusnya",IF(AND(I74="Terencana",ISNUMBER(J74),J74<$C$5),"Target terlewat","OK"))))))) -> OK
A75: 8.10 | B75: Teknologi | C75: Information deletion | D75: Ya | E75: Hukum dan kontrak | F75: - | G75: =COUNTIF(Pemetaan!$B$5:$B$64,A75) -> 0 | H75: UU PDP: data pribadi dihapus bila tidak lagi dibutuhkan; batas retensi perlu ditegakkan. | I75: Sebagian | J75: - | K75: Jadwal retensi, bukti penghapusan data | L75: Sebagian | M75: =IF(AND(D75="Tidak",G75>0),"Konflik: ada risiko terkait",IF(AND(D75="Ya",E75="Risiko",G75=0),"Tidak ada risiko terkait",IF(AND(D75="Ya",I75="-"),"Status kosong",IF(AND(I75="Sudah diterapkan",L75<>"Ada"),"Status Sudah tanpa bukti lengkap",IF(AND(I75="Sebagian",L75="Belum ada"),"Status Sebagian tanpa bukti",IF(AND(I75="Terencana",L75="Ada"),"Terencana tapi bukti sudah ada, cek statusnya",IF(AND(I75="Terencana",ISNUMBER(J75),J75<$C$5),"Target terlewat","OK"))))))) -> OK
A76: 8.11 | B76: Teknologi | C76: Data masking | D76: Ya | E76: Hukum dan kontrak | F76: - | G76: =COUNTIF(Pemetaan!$B$5:$B$64,A76) -> 0 | H76: Menutupi sebagian data KTP dan nomor di dasbor, log, dan lingkungan non-produksi (UU PDP, minimisasi data). | I76: Terencana | J76: =IF(E76="Risiko",$C$3+Evaluasi!$D$6,EDATE($C$3,6)) -> 46489 | K76: Contoh data tertutup di dasbor, log, dan lingkungan uji | L76: Belum ada | M76: =IF(AND(D76="Tidak",G76>0),"Konflik: ada risiko terkait",IF(AND(D76="Ya",E76="Risiko",G76=0),"Tidak ada risiko terkait",IF(AND(D76="Ya",I76="-"),"Status kosong",IF(AND(I76="Sudah diterapkan",L76<>"Ada"),"Status Sudah tanpa bukti lengkap",IF(AND(I76="Sebagian",L76="Belum ada"),"Status Sebagian tanpa bukti",IF(AND(I76="Terencana",L76="Ada"),"Terencana tapi bukti sudah ada, cek statusnya",IF(AND(I76="Terencana",ISNUMBER(J76),J76<$C$5),"Target terlewat","OK"))))))) -> OK
A77: 8.12 | B77: Teknologi | C77: Data leakage prevention | D77: Tidak | E77: Tidak berlaku | F77: - | G77: =COUNTIF(Pemetaan!$B$5:$B$64,A77) -> 0 | H77: Risiko kebocoran data sudah ditangani lewat pembatasan akses (8.3) dan pemantauan akses (8.15, 8.16); alat DLP khusus belum dinilai perlu. | I77: - | J77: - | K77: Justifikasi tertulis pengecualian, bukti kontrol 8.3 dan 8.15 | L77: - | M77: =IF(AND(D77="Tidak",G77>0),"Konflik: ada risiko terkait",IF(AND(D77="Ya",E77="Risiko",G77=0),"Tidak ada risiko terkait",IF(AND(D77="Ya",I77="-"),"Status kosong",IF(AND(I77="Sudah diterapkan",L77<>"Ada"),"Status Sudah tanpa bukti lengkap",IF(AND(I77="Sebagian",L77="Belum ada"),"Status Sebagian tanpa bukti",IF(AND(I77="Terencana",L77="Ada"),"Terencana tapi bukti sudah ada, cek statusnya",IF(AND(I77="Terencana",ISNUMBER(J77),J77<$C$5),"Target terlewat","OK"))))))) -> OK
A78: 8.13 | B78: Teknologi | C78: Information backup | D78: Ya | E78: Risiko | F78: R-15 | G78: =COUNTIF(Pemetaan!$B$5:$B$64,A78) -> 1 | H78: Backup terisolasi dan uji pemulihan. | I78: Terencana | J78: =IF(E78="Risiko",$C$3+Evaluasi!$D$6,EDATE($C$3,6)) -> 46397 | K78: Jadwal backup, hasil uji pemulihan | L78: Belum ada | M78: =IF(AND(D78="Tidak",G78>0),"Konflik: ada risiko terkait",IF(AND(D78="Ya",E78="Risiko",G78=0),"Tidak ada risiko terkait",IF(AND(D78="Ya",I78="-"),"Status kosong",IF(AND(I78="Sudah diterapkan",L78<>"Ada"),"Status Sudah tanpa bukti lengkap",IF(AND(I78="Sebagian",L78="Belum ada"),"Status Sebagian tanpa bukti",IF(AND(I78="Terencana",L78="Ada"),"Terencana tapi bukti sudah ada, cek statusnya",IF(AND(I78="Terencana",ISNUMBER(J78),J78<$C$5),"Target terlewat","OK"))))))) -> OK
A79: 8.14 | B79: Teknologi | C79: Redundancy of information processing facilities | D79: Ya | E79: Risiko | F79: R-15 | G79: =COUNTIF(Pemetaan!$B$5:$B$64,A79) -> 1 | H79: Redundansi untuk ketersediaan layanan. | I79: Terencana | J79: =IF(E79="Risiko",$C$3+Evaluasi!$D$6,EDATE($C$3,6)) -> 46397 | K79: Diagram redundansi, hasil uji failover | L79: Belum ada | M79: =IF(AND(D79="Tidak",G79>0),"Konflik: ada risiko terkait",IF(AND(D79="Ya",E79="Risiko",G79=0),"Tidak ada risiko terkait",IF(AND(D79="Ya",I79="-"),"Status kosong",IF(AND(I79="Sudah diterapkan",L79<>"Ada"),"Status Sudah tanpa bukti lengkap",IF(AND(I79="Sebagian",L79="Belum ada"),"Status Sebagian tanpa bukti",IF(AND(I79="Terencana",L79="Ada"),"Terencana tapi bukti sudah ada, cek statusnya",IF(AND(I79="Terencana",ISNUMBER(J79),J79<$C$5),"Target terlewat","OK"))))))) -> OK
A80: 8.15 | B80: Teknologi | C80: Logging | D80: Ya | E80: Risiko | F80: R-02, R-04, R-13 | G80: =COUNTIF(Pemetaan!$B$5:$B$64,A80) -> 3 | H80: Pencatatan log akses dan perubahan. | I80: Terencana | J80: =IF(E80="Risiko",$C$3+Evaluasi!$D$6,EDATE($C$3,6)) -> 46397 | K80: Konfigurasi log, bukti retensi dan integritas log | L80: Belum ada | M80: =IF(AND(D80="Tidak",G80>0),"Konflik: ada risiko terkait",IF(AND(D80="Ya",E80="Risiko",G80=0),"Tidak ada risiko terkait",IF(AND(D80="Ya",I80="-"),"Status kosong",IF(AND(I80="Sudah diterapkan",L80<>"Ada"),"Status Sudah tanpa bukti lengkap",IF(AND(I80="Sebagian",L80="Belum ada"),"Status Sebagian tanpa bukti",IF(AND(I80="Terencana",L80="Ada"),"Terencana tapi bukti sudah ada, cek statusnya",IF(AND(I80="Terencana",ISNUMBER(J80),J80<$C$5),"Target terlewat","OK"))))))) -> OK
A81: 8.16 | B81: Teknologi | C81: Monitoring activities | D81: Ya | E81: Risiko | F81: R-03, R-10, R-11, R-12, R-13 | G81: =COUNTIF(Pemetaan!$B$5:$B$64,A81) -> 5 | H81: Pemantauan aktivitas tidak wajar. | I81: Terencana | J81: =IF(E81="Risiko",$C$3+Evaluasi!$D$6,EDATE($C$3,6)) -> 46397 | K81: Aturan alert, catatan penanganan alert | L81: Belum ada | M81: =IF(AND(D81="Tidak",G81>0),"Konflik: ada risiko terkait",IF(AND(D81="Ya",E81="Risiko",G81=0),"Tidak ada risiko terkait",IF(AND(D81="Ya",I81="-"),"Status kosong",IF(AND(I81="Sudah diterapkan",L81<>"Ada"),"Status Sudah tanpa bukti lengkap",IF(AND(I81="Sebagian",L81="Belum ada"),"Status Sebagian tanpa bukti",IF(AND(I81="Terencana",L81="Ada"),"Terencana tapi bukti sudah ada, cek statusnya",IF(AND(I81="Terencana",ISNUMBER(J81),J81<$C$5),"Target terlewat","OK"))))))) -> OK
A82: 8.17 | B82: Teknologi | C82: Clock synchronization | D82: Ya | E82: Praktik dasar | F82: - | G82: =COUNTIF(Pemetaan!$B$5:$B$64,A82) -> 0 | H82: Sinkronisasi waktu server agar log dari banyak layanan bisa dikorelasikan (mendukung 8.15). | I82: Sudah diterapkan | J82: - | K82: Konfigurasi sinkronisasi waktu (NTP) server | L82: Ada | M82: =IF(AND(D82="Tidak",G82>0),"Konflik: ada risiko terkait",IF(AND(D82="Ya",E82="Risiko",G82=0),"Tidak ada risiko terkait",IF(AND(D82="Ya",I82="-"),"Status kosong",IF(AND(I82="Sudah diterapkan",L82<>"Ada"),"Status Sudah tanpa bukti lengkap",IF(AND(I82="Sebagian",L82="Belum ada"),"Status Sebagian tanpa bukti",IF(AND(I82="Terencana",L82="Ada"),"Terencana tapi bukti sudah ada, cek statusnya",IF(AND(I82="Terencana",ISNUMBER(J82),J82<$C$5),"Target terlewat","OK"))))))) -> OK
A83: 8.18 | B83: Teknologi | C83: Use of privileged utility programs | D83: Ya | E83: Praktik dasar | F83: - | G83: =COUNTIF(Pemetaan!$B$5:$B$64,A83) -> 0 | H83: Utilitas berhak istimewa (akses langsung ke database, konsol cloud) harus dibatasi. | I83: Sebagian | J83: - | K83: Daftar utilitas berhak istimewa dan pembatasannya | L83: Sebagian | M83: =IF(AND(D83="Tidak",G83>0),"Konflik: ada risiko terkait",IF(AND(D83="Ya",E83="Risiko",G83=0),"Tidak ada risiko terkait",IF(AND(D83="Ya",I83="-"),"Status kosong",IF(AND(I83="Sudah diterapkan",L83<>"Ada"),"Status Sudah tanpa bukti lengkap",IF(AND(I83="Sebagian",L83="Belum ada"),"Status Sebagian tanpa bukti",IF(AND(I83="Terencana",L83="Ada"),"Terencana tapi bukti sudah ada, cek statusnya",IF(AND(I83="Terencana",ISNUMBER(J83),J83<$C$5),"Target terlewat","OK"))))))) -> OK
A84: 8.19 | B84: Teknologi | C84: Installation of software on operational systems | D84: Ya | E84: Praktik dasar | F84: - | G84: =COUNTIF(Pemetaan!$B$5:$B$64,A84) -> 0 | H84: Pemasangan perangkat lunak di server produksi hanya lewat proses rilis. | I84: Sebagian | J84: - | K84: Prosedur dan log instalasi perangkat lunak di produksi | L84: Sebagian | M84: =IF(AND(D84="Tidak",G84>0),"Konflik: ada risiko terkait",IF(AND(D84="Ya",E84="Risiko",G84=0),"Tidak ada risiko terkait",IF(AND(D84="Ya",I84="-"),"Status kosong",IF(AND(I84="Sudah diterapkan",L84<>"Ada"),"Status Sudah tanpa bukti lengkap",IF(AND(I84="Sebagian",L84="Belum ada"),"Status Sebagian tanpa bukti",IF(AND(I84="Terencana",L84="Ada"),"Terencana tapi bukti sudah ada, cek statusnya",IF(AND(I84="Terencana",ISNUMBER(J84),J84<$C$5),"Target terlewat","OK"))))))) -> OK
A85: 8.20 | B85: Teknologi | C85: Networks security | D85: Ya | E85: Risiko | F85: R-10 | G85: =COUNTIF(Pemetaan!$B$5:$B$64,A85) -> 1 | H85: Keamanan jaringan terhadap DDoS. | I85: Terencana | J85: =IF(E85="Risiko",$C$3+Evaluasi!$D$6,EDATE($C$3,6)) -> 46397 | K85: Konfigurasi firewall dan proteksi DDoS | L85: Belum ada | M85: =IF(AND(D85="Tidak",G85>0),"Konflik: ada risiko terkait",IF(AND(D85="Ya",E85="Risiko",G85=0),"Tidak ada risiko terkait",IF(AND(D85="Ya",I85="-"),"Status kosong",IF(AND(I85="Sudah diterapkan",L85<>"Ada"),"Status Sudah tanpa bukti lengkap",IF(AND(I85="Sebagian",L85="Belum ada"),"Status Sebagian tanpa bukti",IF(AND(I85="Terencana",L85="Ada"),"Terencana tapi bukti sudah ada, cek statusnya",IF(AND(I85="Terencana",ISNUMBER(J85),J85<$C$5),"Target terlewat","OK"))))))) -> OK
A86: 8.21 | B86: Teknologi | C86: Security of network services | D86: Ya | E86: Risiko | F86: R-10 | G86: =COUNTIF(Pemetaan!$B$5:$B$64,A86) -> 1 | H86: Keamanan layanan jaringan (proteksi DDoS penyedia). | I86: Terencana | J86: =IF(E86="Risiko",$C$3+Evaluasi!$D$6,EDATE($C$3,6)) -> 46397 | K86: Perjanjian layanan jaringan, konfigurasi rate limiting | L86: Belum ada | M86: =IF(AND(D86="Tidak",G86>0),"Konflik: ada risiko terkait",IF(AND(D86="Ya",E86="Risiko",G86=0),"Tidak ada risiko terkait",IF(AND(D86="Ya",I86="-"),"Status kosong",IF(AND(I86="Sudah diterapkan",L86<>"Ada"),"Status Sudah tanpa bukti lengkap",IF(AND(I86="Sebagian",L86="Belum ada"),"Status Sebagian tanpa bukti",IF(AND(I86="Terencana",L86="Ada"),"Terencana tapi bukti sudah ada, cek statusnya",IF(AND(I86="Terencana",ISNUMBER(J86),J86<$C$5),"Target terlewat","OK"))))))) -> OK
A87: 8.22 | B87: Teknologi | C87: Segregation of networks | D87: Ya | E87: Praktik dasar | F87: - | G87: =COUNTIF(Pemetaan!$B$5:$B$64,A87) -> 0 | H87: Pemisahan jaringan kantor dari lingkungan produksi dan antar layanan microservices. | I87: Sebagian | J87: - | K87: Diagram segmentasi jaringan, aturan firewall | L87: Sebagian | M87: =IF(AND(D87="Tidak",G87>0),"Konflik: ada risiko terkait",IF(AND(D87="Ya",E87="Risiko",G87=0),"Tidak ada risiko terkait",IF(AND(D87="Ya",I87="-"),"Status kosong",IF(AND(I87="Sudah diterapkan",L87<>"Ada"),"Status Sudah tanpa bukti lengkap",IF(AND(I87="Sebagian",L87="Belum ada"),"Status Sebagian tanpa bukti",IF(AND(I87="Terencana",L87="Ada"),"Terencana tapi bukti sudah ada, cek statusnya",IF(AND(I87="Terencana",ISNUMBER(J87),J87<$C$5),"Target terlewat","OK"))))))) -> OK
A88: 8.23 | B88: Teknologi | C88: Web filtering | D88: Ya | E88: Risiko | F88: R-18 | G88: =COUNTIF(Pemetaan!$B$5:$B$64,A88) -> 1 | H88: Penyaringan web dan email. | I88: Terencana | J88: =IF(E88="Risiko",$C$3+Evaluasi!$D$6,EDATE($C$3,6)) -> 46397 | K88: Konfigurasi filter web dan email | L88: Belum ada | M88: =IF(AND(D88="Tidak",G88>0),"Konflik: ada risiko terkait",IF(AND(D88="Ya",E88="Risiko",G88=0),"Tidak ada risiko terkait",IF(AND(D88="Ya",I88="-"),"Status kosong",IF(AND(I88="Sudah diterapkan",L88<>"Ada"),"Status Sudah tanpa bukti lengkap",IF(AND(I88="Sebagian",L88="Belum ada"),"Status Sebagian tanpa bukti",IF(AND(I88="Terencana",L88="Ada"),"Terencana tapi bukti sudah ada, cek statusnya",IF(AND(I88="Terencana",ISNUMBER(J88),J88<$C$5),"Target terlewat","OK"))))))) -> OK
A89: 8.24 | B89: Teknologi | C89: Use of cryptography | D89: Ya | E89: Risiko | F89: R-03, R-05 | G89: =COUNTIF(Pemetaan!$B$5:$B$64,A89) -> 2 | H89: Enkripsi dan manajemen kunci. | I89: Terencana | J89: =IF(E89="Risiko",$C$3+Evaluasi!$D$6,EDATE($C$3,6)) -> 46397 | K89: Kebijakan kriptografi, konfigurasi enkripsi dan manajemen kunci | L89: Belum ada | M89: =IF(AND(D89="Tidak",G89>0),"Konflik: ada risiko terkait",IF(AND(D89="Ya",E89="Risiko",G89=0),"Tidak ada risiko terkait",IF(AND(D89="Ya",I89="-"),"Status kosong",IF(AND(I89="Sudah diterapkan",L89<>"Ada"),"Status Sudah tanpa bukti lengkap",IF(AND(I89="Sebagian",L89="Belum ada"),"Status Sebagian tanpa bukti",IF(AND(I89="Terencana",L89="Ada"),"Terencana tapi bukti sudah ada, cek statusnya",IF(AND(I89="Terencana",ISNUMBER(J89),J89<$C$5),"Target terlewat","OK"))))))) -> OK
A90: 8.25 | B90: Teknologi | C90: Secure development life cycle | D90: Ya | E90: Risiko | F90: R-07 | G90: =COUNTIF(Pemetaan!$B$5:$B$64,A90) -> 1 | H90: Siklus pengembangan aman. | I90: Terencana | J90: =IF(E90="Risiko",$C$3+Evaluasi!$D$6,EDATE($C$3,6)) -> 46397 | K90: Prosedur siklus pengembangan aman, checklist rilis | L90: Belum ada | M90: =IF(AND(D90="Tidak",G90>0),"Konflik: ada risiko terkait",IF(AND(D90="Ya",E90="Risiko",G90=0),"Tidak ada risiko terkait",IF(AND(D90="Ya",I90="-"),"Status kosong",IF(AND(I90="Sudah diterapkan",L90<>"Ada"),"Status Sudah tanpa bukti lengkap",IF(AND(I90="Sebagian",L90="Belum ada"),"Status Sebagian tanpa bukti",IF(AND(I90="Terencana",L90="Ada"),"Terencana tapi bukti sudah ada, cek statusnya",IF(AND(I90="Terencana",ISNUMBER(J90),J90<$C$5),"Target terlewat","OK"))))))) -> OK
A91: 8.26 | B91: Teknologi | C91: Application security requirements | D91: Ya | E91: Risiko | F91: R-01, R-11 | G91: =COUNTIF(Pemetaan!$B$5:$B$64,A91) -> 2 | H91: Persyaratan keamanan aplikasi dan API. | I91: Terencana | J91: =IF(E91="Risiko",$C$3+Evaluasi!$D$6,EDATE($C$3,6)) -> 46397 | K91: Dokumen persyaratan keamanan, hasil review | L91: Belum ada | M91: =IF(AND(D91="Tidak",G91>0),"Konflik: ada risiko terkait",IF(AND(D91="Ya",E91="Risiko",G91=0),"Tidak ada risiko terkait",IF(AND(D91="Ya",I91="-"),"Status kosong",IF(AND(I91="Sudah diterapkan",L91<>"Ada"),"Status Sudah tanpa bukti lengkap",IF(AND(I91="Sebagian",L91="Belum ada"),"Status Sebagian tanpa bukti",IF(AND(I91="Terencana",L91="Ada"),"Terencana tapi bukti sudah ada, cek statusnya",IF(AND(I91="Terencana",ISNUMBER(J91),J91<$C$5),"Target terlewat","OK"))))))) -> OK
A92: 8.27 | B92: Teknologi | C92: Secure system architecture and engineering principles | D92: Ya | E92: Praktik dasar | F92: - | G92: =COUNTIF(Pemetaan!$B$5:$B$64,A92) -> 0 | H92: Prinsip arsitektur aman untuk microservices dan integrasi bank mitra. | I92: Sebagian | J92: - | K92: Dokumen arsitektur dan prinsip desain aman | L92: Sebagian | M92: =IF(AND(D92="Tidak",G92>0),"Konflik: ada risiko terkait",IF(AND(D92="Ya",E92="Risiko",G92=0),"Tidak ada risiko terkait",IF(AND(D92="Ya",I92="-"),"Status kosong",IF(AND(I92="Sudah diterapkan",L92<>"Ada"),"Status Sudah tanpa bukti lengkap",IF(AND(I92="Sebagian",L92="Belum ada"),"Status Sebagian tanpa bukti",IF(AND(I92="Terencana",L92="Ada"),"Terencana tapi bukti sudah ada, cek statusnya",IF(AND(I92="Terencana",ISNUMBER(J92),J92<$C$5),"Target terlewat","OK"))))))) -> OK
A93: 8.28 | B93: Teknologi | C93: Secure coding | D93: Ya | E93: Risiko | F93: R-01, R-05, R-11 | G93: =COUNTIF(Pemetaan!$B$5:$B$64,A93) -> 3 | H93: Praktik pengodean aman. | I93: Terencana | J93: =IF(E93="Risiko",$C$3+Evaluasi!$D$6,EDATE($C$3,6)) -> 46397 | K93: Standar pengodean aman, hasil code review | L93: Belum ada | M93: =IF(AND(D93="Tidak",G93>0),"Konflik: ada risiko terkait",IF(AND(D93="Ya",E93="Risiko",G93=0),"Tidak ada risiko terkait",IF(AND(D93="Ya",I93="-"),"Status kosong",IF(AND(I93="Sudah diterapkan",L93<>"Ada"),"Status Sudah tanpa bukti lengkap",IF(AND(I93="Sebagian",L93="Belum ada"),"Status Sebagian tanpa bukti",IF(AND(I93="Terencana",L93="Ada"),"Terencana tapi bukti sudah ada, cek statusnya",IF(AND(I93="Terencana",ISNUMBER(J93),J93<$C$5),"Target terlewat","OK"))))))) -> OK
A94: 8.29 | B94: Teknologi | C94: Security testing in development and acceptance | D94: Ya | E94: Risiko | F94: R-01, R-11 | G94: =COUNTIF(Pemetaan!$B$5:$B$64,A94) -> 2 | H94: Pengujian keamanan sebelum rilis. | I94: Terencana | J94: =IF(E94="Risiko",$C$3+Evaluasi!$D$6,EDATE($C$3,6)) -> 46397 | K94: Laporan SAST dan pentest, tiket perbaikan | L94: Belum ada | M94: =IF(AND(D94="Tidak",G94>0),"Konflik: ada risiko terkait",IF(AND(D94="Ya",E94="Risiko",G94=0),"Tidak ada risiko terkait",IF(AND(D94="Ya",I94="-"),"Status kosong",IF(AND(I94="Sudah diterapkan",L94<>"Ada"),"Status Sudah tanpa bukti lengkap",IF(AND(I94="Sebagian",L94="Belum ada"),"Status Sebagian tanpa bukti",IF(AND(I94="Terencana",L94="Ada"),"Terencana tapi bukti sudah ada, cek statusnya",IF(AND(I94="Terencana",ISNUMBER(J94),J94<$C$5),"Target terlewat","OK"))))))) -> OK
A95: 8.30 | B95: Teknologi | C95: Outsourced development | D95: Tidak | E95: Tidak berlaku | F95: - | G95: =COUNTIF(Pemetaan!$B$5:$B$64,A95) -> 0 | H95: Pengembangan aplikasi dilakukan tim engineering internal; tidak ada pengembangan yang dialihdayakan. | I95: - | J95: - | K95: Justifikasi tertulis pengecualian, daftar tim pengembang internal | L95: - | M95: =IF(AND(D95="Tidak",G95>0),"Konflik: ada risiko terkait",IF(AND(D95="Ya",E95="Risiko",G95=0),"Tidak ada risiko terkait",IF(AND(D95="Ya",I95="-"),"Status kosong",IF(AND(I95="Sudah diterapkan",L95<>"Ada"),"Status Sudah tanpa bukti lengkap",IF(AND(I95="Sebagian",L95="Belum ada"),"Status Sebagian tanpa bukti",IF(AND(I95="Terencana",L95="Ada"),"Terencana tapi bukti sudah ada, cek statusnya",IF(AND(I95="Terencana",ISNUMBER(J95),J95<$C$5),"Target terlewat","OK"))))))) -> OK
A96: 8.31 | B96: Teknologi | C96: Separation of development, test and production environments | D96: Ya | E96: Praktik dasar | F96: - | G96: =COUNTIF(Pemetaan!$B$5:$B$64,A96) -> 0 | H96: Lingkungan pengembangan, uji, dan produksi dipisah. | I96: Sebagian | J96: - | K96: Diagram lingkungan, bukti pemisahan akses | L96: Sebagian | M96: =IF(AND(D96="Tidak",G96>0),"Konflik: ada risiko terkait",IF(AND(D96="Ya",E96="Risiko",G96=0),"Tidak ada risiko terkait",IF(AND(D96="Ya",I96="-"),"Status kosong",IF(AND(I96="Sudah diterapkan",L96<>"Ada"),"Status Sudah tanpa bukti lengkap",IF(AND(I96="Sebagian",L96="Belum ada"),"Status Sebagian tanpa bukti",IF(AND(I96="Terencana",L96="Ada"),"Terencana tapi bukti sudah ada, cek statusnya",IF(AND(I96="Terencana",ISNUMBER(J96),J96<$C$5),"Target terlewat","OK"))))))) -> OK
A97: 8.32 | B97: Teknologi | C97: Change management | D97: Ya | E97: Risiko | F97: R-07 | G97: =COUNTIF(Pemetaan!$B$5:$B$64,A97) -> 1 | H97: Manajemen perubahan kode dan pipeline. | I97: Terencana | J97: =IF(E97="Risiko",$C$3+Evaluasi!$D$6,EDATE($C$3,6)) -> 46397 | K97: Catatan permintaan perubahan dan persetujuan, konfigurasi branch protection | L97: Belum ada | M97: =IF(AND(D97="Tidak",G97>0),"Konflik: ada risiko terkait",IF(AND(D97="Ya",E97="Risiko",G97=0),"Tidak ada risiko terkait",IF(AND(D97="Ya",I97="-"),"Status kosong",IF(AND(I97="Sudah diterapkan",L97<>"Ada"),"Status Sudah tanpa bukti lengkap",IF(AND(I97="Sebagian",L97="Belum ada"),"Status Sebagian tanpa bukti",IF(AND(I97="Terencana",L97="Ada"),"Terencana tapi bukti sudah ada, cek statusnya",IF(AND(I97="Terencana",ISNUMBER(J97),J97<$C$5),"Target terlewat","OK"))))))) -> OK
A98: 8.33 | B98: Teknologi | C98: Test information | D98: Ya | E98: Hukum dan kontrak | F98: - | G98: =COUNTIF(Pemetaan!$B$5:$B$64,A98) -> 0 | H98: Data pengguna nyata tidak dipakai di lingkungan uji tanpa perlindungan (UU PDP). | I98: Sebagian | J98: - | K98: Bukti pengaturan data uji | L98: Sebagian | M98: =IF(AND(D98="Tidak",G98>0),"Konflik: ada risiko terkait",IF(AND(D98="Ya",E98="Risiko",G98=0),"Tidak ada risiko terkait",IF(AND(D98="Ya",I98="-"),"Status kosong",IF(AND(I98="Sudah diterapkan",L98<>"Ada"),"Status Sudah tanpa bukti lengkap",IF(AND(I98="Sebagian",L98="Belum ada"),"Status Sebagian tanpa bukti",IF(AND(I98="Terencana",L98="Ada"),"Terencana tapi bukti sudah ada, cek statusnya",IF(AND(I98="Terencana",ISNUMBER(J98),J98<$C$5),"Target terlewat","OK"))))))) -> OK
A99: 8.34 | B99: Teknologi | C99: Protection of information systems during audit testing | D99: Ya | E99: Praktik dasar | F99: - | G99: =COUNTIF(Pemetaan!$B$5:$B$64,A99) -> 0 | H99: Pengujian keamanan dan audit tidak boleh mengganggu sistem produksi. | I99: Sebagian | J99: - | K99: Rencana dan persetujuan pengujian keamanan | L99: Sebagian | M99: =IF(AND(D99="Tidak",G99>0),"Konflik: ada risiko terkait",IF(AND(D99="Ya",E99="Risiko",G99=0),"Tidak ada risiko terkait",IF(AND(D99="Ya",I99="-"),"Status kosong",IF(AND(I99="Sudah diterapkan",L99<>"Ada"),"Status Sudah tanpa bukti lengkap",IF(AND(I99="Sebagian",L99="Belum ada"),"Status Sebagian tanpa bukti",IF(AND(I99="Terencana",L99="Ada"),"Terencana tapi bukti sudah ada, cek statusnya",IF(AND(I99="Terencana",ISNUMBER(J99),J99<$C$5),"Target terlewat","OK"))))))) -> OK
A101: Aturan cek konsistensi (kolom Cek konsistensi)
A102: 1 | B102: Kontrol Tidak berlaku tetapi masih terhubung ke risiko (Jml risiko > 0): "Konflik: ada risiko terkait".
A103: 2 | B103: Kontrol berlaku dengan dasar Risiko tetapi tidak ada risiko terkait: "Tidak ada risiko terkait".
...
